{
  "ticker": "NDAQ",
  "source": "https://query2.finance.yahoo.com/v8/finance/chart/NDAQ?range=2y&interval=1d&events=history",
  "fetchedAt": "2026-05-12T06:14:32.082Z",
  "bars": [
    {
      "date": "2024-05-13",
      "close": 59.07885
    },
    {
      "date": "2024-05-14",
      "close": 58.87418
    },
    {
      "date": "2024-05-15",
      "close": 59.790283
    },
    {
      "date": "2024-05-16",
      "close": 60.647923
    },
    {
      "date": "2024-05-17",
      "close": 61.164444
    },
    {
      "date": "2024-05-20",
      "close": 60.86232
    },
    {
      "date": "2024-05-21",
      "close": 60.852581
    },
    {
      "date": "2024-05-22",
      "close": 60.86232
    },
    {
      "date": "2024-05-23",
      "close": 59.955967
    },
    {
      "date": "2024-05-24",
      "close": 60.647923
    },
    {
      "date": "2024-05-28",
      "close": 58.669525
    },
    {
      "date": "2024-05-29",
      "close": 58.328423
    },
    {
      "date": "2024-05-30",
      "close": 57.548759
    },
    {
      "date": "2024-05-31",
      "close": 57.52927
    },
    {
      "date": "2024-06-03",
      "close": 57.246651
    },
    {
      "date": "2024-06-04",
      "close": 57.919102
    },
    {
      "date": "2024-06-05",
      "close": 58.191986
    },
    {
      "date": "2024-06-06",
      "close": 57.753422
    },
    {
      "date": "2024-06-07",
      "close": 57.285625
    },
    {
      "date": "2024-06-10",
      "close": 57.792404
    },
    {
      "date": "2024-06-11",
      "close": 57.519531
    },
    {
      "date": "2024-06-12",
      "close": 58.036053
    },
    {
      "date": "2024-06-13",
      "close": 57.694958
    },
    {
      "date": "2024-06-14",
      "close": 57.34267
    },
    {
      "date": "2024-06-17",
      "close": 57.372036
    },
    {
      "date": "2024-06-18",
      "close": 57.724308
    },
    {
      "date": "2024-06-20",
      "close": 57.95916
    },
    {
      "date": "2024-06-21",
      "close": 58.957275
    },
    {
      "date": "2024-06-24",
      "close": 58.810486
    },
    {
      "date": "2024-06-25",
      "close": 58.624565
    },
    {
      "date": "2024-06-26",
      "close": 58.477787
    },
    {
      "date": "2024-06-27",
      "close": 58.888771
    },
    {
      "date": "2024-06-28",
      "close": 58.967056
    },
    {
      "date": "2024-07-01",
      "close": 58.203796
    },
    {
      "date": "2024-07-02",
      "close": 58.673496
    },
    {
      "date": "2024-07-03",
      "close": 58.849636
    },
    {
      "date": "2024-07-05",
      "close": 59.084484
    },
    {
      "date": "2024-07-08",
      "close": 59.143196
    },
    {
      "date": "2024-07-09",
      "close": 59.505257
    },
    {
      "date": "2024-07-10",
      "close": 60.307659
    },
    {
      "date": "2024-07-11",
      "close": 60.865437
    },
    {
      "date": "2024-07-12",
      "close": 61.35471
    },
    {
      "date": "2024-07-15",
      "close": 61.64827
    },
    {
      "date": "2024-07-16",
      "close": 61.941833
    },
    {
      "date": "2024-07-17",
      "close": 62.127754
    },
    {
      "date": "2024-07-18",
      "close": 61.139423
    },
    {
      "date": "2024-07-19",
      "close": 61.168777
    },
    {
      "date": "2024-07-22",
      "close": 61.677616
    },
    {
      "date": "2024-07-23",
      "close": 61.775482
    },
    {
      "date": "2024-07-24",
      "close": 61.384064
    },
    {
      "date": "2024-07-25",
      "close": 65.816864
    },
    {
      "date": "2024-07-26",
      "close": 65.523308
    },
    {
      "date": "2024-07-29",
      "close": 66.462708
    },
    {
      "date": "2024-07-30",
      "close": 67.666321
    },
    {
      "date": "2024-07-31",
      "close": 66.227852
    },
    {
      "date": "2024-08-01",
      "close": 65.87558
    },
    {
      "date": "2024-08-02",
      "close": 65.425453
    },
    {
      "date": "2024-08-05",
      "close": 63.01823
    },
    {
      "date": "2024-08-06",
      "close": 64.769821
    },
    {
      "date": "2024-08-07",
      "close": 65.366737
    },
    {
      "date": "2024-08-08",
      "close": 66.580132
    },
    {
      "date": "2024-08-09",
      "close": 66.629059
    },
    {
      "date": "2024-08-12",
      "close": 66.521416
    },
    {
      "date": "2024-08-13",
      "close": 67.441246
    },
    {
      "date": "2024-08-14",
      "close": 67.813095
    },
    {
      "date": "2024-08-15",
      "close": 68.282806
    },
    {
      "date": "2024-08-16",
      "close": 68.331741
    },
    {
      "date": "2024-08-19",
      "close": 68.468727
    },
    {
      "date": "2024-08-20",
      "close": 68.586143
    },
    {
      "date": "2024-08-21",
      "close": 68.73291
    },
    {
      "date": "2024-08-22",
      "close": 69.114548
    },
    {
      "date": "2024-08-23",
      "close": 68.840569
    },
    {
      "date": "2024-08-26",
      "close": 69.075409
    },
    {
      "date": "2024-08-27",
      "close": 69.525543
    },
    {
      "date": "2024-08-28",
      "close": 69.427681
    },
    {
      "date": "2024-08-29",
      "close": 69.662552
    },
    {
      "date": "2024-08-30",
      "close": 70.533447
    },
    {
      "date": "2024-09-03",
      "close": 69.858253
    },
    {
      "date": "2024-09-04",
      "close": 71.903412
    },
    {
      "date": "2024-09-05",
      "close": 71.825134
    },
    {
      "date": "2024-09-06",
      "close": 70.406235
    },
    {
      "date": "2024-09-09",
      "close": 70.112679
    },
    {
      "date": "2024-09-10",
      "close": 70.210533
    },
    {
      "date": "2024-09-11",
      "close": 70.533447
    },
    {
      "date": "2024-09-12",
      "close": 71.012932
    },
    {
      "date": "2024-09-13",
      "close": 71.670731
    },
    {
      "date": "2024-09-16",
      "close": 71.965271
    },
    {
      "date": "2024-09-17",
      "close": 71.37619
    },
    {
      "date": "2024-09-18",
      "close": 71.572556
    },
    {
      "date": "2024-09-19",
      "close": 72.937248
    },
    {
      "date": "2024-09-20",
      "close": 72.937248
    },
    {
      "date": "2024-09-23",
      "close": 72.662354
    },
    {
      "date": "2024-09-24",
      "close": 72.328545
    },
    {
      "date": "2024-09-25",
      "close": 71.710014
    },
    {
      "date": "2024-09-26",
      "close": 71.238747
    },
    {
      "date": "2024-09-27",
      "close": 71.278015
    },
    {
      "date": "2024-09-30",
      "close": 71.680565
    },
    {
      "date": "2024-10-01",
      "close": 71.719826
    },
    {
      "date": "2024-10-02",
      "close": 71.660912
    },
    {
      "date": "2024-10-03",
      "close": 71.592194
    },
    {
      "date": "2024-10-04",
      "close": 70.806763
    },
    {
      "date": "2024-10-07",
      "close": 69.579521
    },
    {
      "date": "2024-10-08",
      "close": 70.875488
    },
    {
      "date": "2024-10-09",
      "close": 71.150391
    },
    {
      "date": "2024-10-10",
      "close": 70.531845
    },
    {
      "date": "2024-10-11",
      "close": 70.315857
    },
    {
      "date": "2024-10-14",
      "close": 71.248566
    },
    {
      "date": "2024-10-15",
      "close": 71.700195
    },
    {
      "date": "2024-10-16",
      "close": 72.416901
    },
    {
      "date": "2024-10-17",
      "close": 72.789978
    },
    {
      "date": "2024-10-18",
      "close": 73.545959
    },
    {
      "date": "2024-10-21",
      "close": 72.94706
    },
    {
      "date": "2024-10-22",
      "close": 72.937248
    },
    {
      "date": "2024-10-23",
      "close": 72.564171
    },
    {
      "date": "2024-10-24",
      "close": 73.869942
    },
    {
      "date": "2024-10-25",
      "close": 73.329971
    },
    {
      "date": "2024-10-28",
      "close": 73.968117
    },
    {
      "date": "2024-10-29",
      "close": 74.50811
    },
    {
      "date": "2024-10-30",
      "close": 74.174294
    },
    {
      "date": "2024-10-31",
      "close": 72.573975
    },
    {
      "date": "2024-11-01",
      "close": 72.966698
    },
    {
      "date": "2024-11-04",
      "close": 73.447777
    },
    {
      "date": "2024-11-05",
      "close": 74.753563
    },
    {
      "date": "2024-11-06",
      "close": 76.177147
    },
    {
      "date": "2024-11-07",
      "close": 76.756409
    },
    {
      "date": "2024-11-08",
      "close": 77.257118
    },
    {
      "date": "2024-11-11",
      "close": 78.209473
    },
    {
      "date": "2024-11-12",
      "close": 77.689117
    },
    {
      "date": "2024-11-13",
      "close": 78.415649
    },
    {
      "date": "2024-11-14",
      "close": 76.638596
    },
    {
      "date": "2024-11-15",
      "close": 77.325859
    },
    {
      "date": "2024-11-18",
      "close": 78.327278
    },
    {
      "date": "2024-11-19",
      "close": 78.700356
    },
    {
      "date": "2024-11-20",
      "close": 78.621811
    },
    {
      "date": "2024-11-21",
      "close": 79.407242
    },
    {
      "date": "2024-11-22",
      "close": 79.593781
    },
    {
      "date": "2024-11-25",
      "close": 80.035583
    },
    {
      "date": "2024-11-26",
      "close": 81.145012
    },
    {
      "date": "2024-11-27",
      "close": 81.537735
    },
    {
      "date": "2024-11-29",
      "close": 81.478828
    },
    {
      "date": "2024-12-02",
      "close": 80.163223
    },
    {
      "date": "2024-12-03",
      "close": 79.515244
    },
    {
      "date": "2024-12-04",
      "close": 79.358154
    },
    {
      "date": "2024-12-05",
      "close": 79.790146
    },
    {
      "date": "2024-12-06",
      "close": 79.898453
    },
    {
      "date": "2024-12-09",
      "close": 78.480492
    },
    {
      "date": "2024-12-10",
      "close": 79.199326
    },
    {
      "date": "2024-12-11",
      "close": 80.065857
    },
    {
      "date": "2024-12-12",
      "close": 79.632591
    },
    {
      "date": "2024-12-13",
      "close": 78.894073
    },
    {
      "date": "2024-12-16",
      "close": 79.228859
    },
    {
      "date": "2024-12-17",
      "close": 78.391876
    },
    {
      "date": "2024-12-18",
      "close": 76.284615
    },
    {
      "date": "2024-12-19",
      "close": 76.195992
    },
    {
      "date": "2024-12-20",
      "close": 76.511086
    },
    {
      "date": "2024-12-23",
      "close": 76.747421
    },
    {
      "date": "2024-12-24",
      "close": 77.712433
    },
    {
      "date": "2024-12-26",
      "close": 77.90937
    },
    {
      "date": "2024-12-27",
      "close": 77.220078
    },
    {
      "date": "2024-12-30",
      "close": 76.215691
    },
    {
      "date": "2024-12-31",
      "close": 76.127052
    },
    {
      "date": "2025-01-02",
      "close": 76.245232
    },
    {
      "date": "2025-01-03",
      "close": 77.023148
    },
    {
      "date": "2025-01-06",
      "close": 75.644554
    },
    {
      "date": "2025-01-07",
      "close": 75.191605
    },
    {
      "date": "2025-01-08",
      "close": 76.826202
    },
    {
      "date": "2025-01-10",
      "close": 74.718941
    },
    {
      "date": "2025-01-13",
      "close": 75.014351
    },
    {
      "date": "2025-01-14",
      "close": 75.08329
    },
    {
      "date": "2025-01-15",
      "close": 75.802116
    },
    {
      "date": "2025-01-16",
      "close": 77.190536
    },
    {
      "date": "2025-01-17",
      "close": 77.62381
    },
    {
      "date": "2025-01-21",
      "close": 78.647896
    },
    {
      "date": "2025-01-22",
      "close": 79.593208
    },
    {
      "date": "2025-01-23",
      "close": 79.790146
    },
    {
      "date": "2025-01-24",
      "close": 79.90831
    },
    {
      "date": "2025-01-27",
      "close": 80.213554
    },
    {
      "date": "2025-01-28",
      "close": 79.947701
    },
    {
      "date": "2025-01-29",
      "close": 80.479439
    },
    {
      "date": "2025-01-30",
      "close": 81.021011
    },
    {
      "date": "2025-01-31",
      "close": 81.080093
    },
    {
      "date": "2025-02-03",
      "close": 80.666519
    },
    {
      "date": "2025-02-04",
      "close": 80.469597
    },
    {
      "date": "2025-02-05",
      "close": 81.59214
    },
    {
      "date": "2025-02-06",
      "close": 82.478371
    },
    {
      "date": "2025-02-07",
      "close": 81.55275
    },
    {
      "date": "2025-02-10",
      "close": 79.967392
    },
    {
      "date": "2025-02-11",
      "close": 79.061462
    },
    {
      "date": "2025-02-12",
      "close": 78.697128
    },
    {
      "date": "2025-02-13",
      "close": 80.440048
    },
    {
      "date": "2025-02-14",
      "close": 79.671989
    },
    {
      "date": "2025-02-18",
      "close": 79.996933
    },
    {
      "date": "2025-02-19",
      "close": 81.326271
    },
    {
      "date": "2025-02-20",
      "close": 81.277039
    },
    {
      "date": "2025-02-21",
      "close": 79.829529
    },
    {
      "date": "2025-02-24",
      "close": 78.716827
    },
    {
      "date": "2025-02-25",
      "close": 78.332794
    },
    {
      "date": "2025-02-26",
      "close": 78.8153
    },
    {
      "date": "2025-02-27",
      "close": 79.56366
    },
    {
      "date": "2025-02-28",
      "close": 81.513367
    },
    {
      "date": "2025-03-03",
      "close": 80.715767
    },
    {
      "date": "2025-03-04",
      "close": 77.554886
    },
    {
      "date": "2025-03-05",
      "close": 77.594269
    },
    {
      "date": "2025-03-06",
      "close": 75.004509
    },
    {
      "date": "2025-03-07",
      "close": 73.517624
    },
    {
      "date": "2025-03-10",
      "close": 71.735306
    },
    {
      "date": "2025-03-11",
      "close": 71.183876
    },
    {
      "date": "2025-03-12",
      "close": 71.863319
    },
    {
      "date": "2025-03-13",
      "close": 71.065712
    },
    {
      "date": "2025-03-14",
      "close": 72.379738
    },
    {
      "date": "2025-03-17",
      "close": 73.654236
    },
    {
      "date": "2025-03-18",
      "close": 74.395218
    },
    {
      "date": "2025-03-19",
      "close": 75.659836
    },
    {
      "date": "2025-03-20",
      "close": 75.985878
    },
    {
      "date": "2025-03-21",
      "close": 74.64222
    },
    {
      "date": "2025-03-24",
      "close": 76.479874
    },
    {
      "date": "2025-03-25",
      "close": 76.736732
    },
    {
      "date": "2025-03-26",
      "close": 76.598427
    },
    {
      "date": "2025-03-27",
      "close": 75.442482
    },
    {
      "date": "2025-03-28",
      "close": 74.009911
    },
    {
      "date": "2025-03-31",
      "close": 74.948486
    },
    {
      "date": "2025-04-01",
      "close": 75.126328
    },
    {
      "date": "2025-04-02",
      "close": 77.359169
    },
    {
      "date": "2025-04-03",
      "close": 72.903366
    },
    {
      "date": "2025-04-04",
      "close": 67.429924
    },
    {
      "date": "2025-04-07",
      "close": 66.926056
    },
    {
      "date": "2025-04-08",
      "close": 65.602158
    },
    {
      "date": "2025-04-09",
      "close": 71.124985
    },
    {
      "date": "2025-04-10",
      "close": 69.455299
    },
    {
      "date": "2025-04-11",
      "close": 70.670517
    },
    {
      "date": "2025-04-14",
      "close": 71.905502
    },
    {
      "date": "2025-04-15",
      "close": 72.29081
    },
    {
      "date": "2025-04-16",
      "close": 70.828598
    },
    {
      "date": "2025-04-17",
      "close": 71.312706
    },
    {
      "date": "2025-04-21",
      "close": 69.810974
    },
    {
      "date": "2025-04-22",
      "close": 71.816582
    },
    {
      "date": "2025-04-23",
      "close": 72.616837
    },
    {
      "date": "2025-04-24",
      "close": 73.841942
    },
    {
      "date": "2025-04-25",
      "close": 74.454498
    },
    {
      "date": "2025-04-28",
      "close": 74.197617
    },
    {
      "date": "2025-04-29",
      "close": 75.027534
    },
    {
      "date": "2025-04-30",
      "close": 75.294281
    },
    {
      "date": "2025-05-01",
      "close": 75.225128
    },
    {
      "date": "2025-05-02",
      "close": 77.240608
    },
    {
      "date": "2025-05-05",
      "close": 77.250496
    },
    {
      "date": "2025-05-06",
      "close": 77.141815
    },
    {
      "date": "2025-05-07",
      "close": 77.625923
    },
    {
      "date": "2025-05-08",
      "close": 78.050758
    },
    {
      "date": "2025-05-09",
      "close": 78.258232
    },
    {
      "date": "2025-05-12",
      "close": 79.779739
    },
    {
      "date": "2025-05-13",
      "close": 80.589882
    },
    {
      "date": "2025-05-14",
      "close": 80.086006
    },
    {
      "date": "2025-05-15",
      "close": 80.30336
    },
    {
      "date": "2025-05-16",
      "close": 80.915924
    },
    {
      "date": "2025-05-19",
      "close": 80.975197
    },
    {
      "date": "2025-05-20",
      "close": 80.846748
    },
    {
      "date": "2025-05-21",
      "close": 79.671051
    },
    {
      "date": "2025-05-22",
      "close": 80.234207
    },
    {
      "date": "2025-05-23",
      "close": 80.797356
    },
    {
      "date": "2025-05-27",
      "close": 82.061974
    },
    {
      "date": "2025-05-28",
      "close": 81.558105
    },
    {
      "date": "2025-05-29",
      "close": 82.378136
    },
    {
      "date": "2025-05-30",
      "close": 82.536209
    },
    {
      "date": "2025-06-02",
      "close": 82.990685
    },
    {
      "date": "2025-06-03",
      "close": 82.802956
    },
    {
      "date": "2025-06-04",
      "close": 82.862251
    },
    {
      "date": "2025-06-05",
      "close": 82.990685
    },
    {
      "date": "2025-06-06",
      "close": 84.581337
    },
    {
      "date": "2025-06-09",
      "close": 84.620857
    },
    {
      "date": "2025-06-10",
      "close": 85.035812
    },
    {
      "date": "2025-06-11",
      "close": 85.747154
    },
    {
      "date": "2025-06-12",
      "close": 85.855827
    },
    {
      "date": "2025-06-13",
      "close": 84.825127
    },
    {
      "date": "2025-06-16",
      "close": 85.905396
    },
    {
      "date": "2025-06-17",
      "close": 85.181915
    },
    {
      "date": "2025-06-18",
      "close": 85.59816
    },
    {
      "date": "2025-06-20",
      "close": 85.330566
    },
    {
      "date": "2025-06-23",
      "close": 85.954948
    },
    {
      "date": "2025-06-24",
      "close": 87.33252
    },
    {
      "date": "2025-06-25",
      "close": 87.263153
    },
    {
      "date": "2025-06-26",
      "close": 87.600105
    },
    {
      "date": "2025-06-27",
      "close": 88.283943
    },
    {
      "date": "2025-06-30",
      "close": 88.620911
    },
    {
      "date": "2025-07-01",
      "close": 88.145195
    },
    {
      "date": "2025-07-02",
      "close": 88.720001
    },
    {
      "date": "2025-07-03",
      "close": 89.265091
    },
    {
      "date": "2025-07-07",
      "close": 89.740814
    },
    {
      "date": "2025-07-08",
      "close": 87.798317
    },
    {
      "date": "2025-07-09",
      "close": 89.027245
    },
    {
      "date": "2025-07-10",
      "close": 89.919205
    },
    {
      "date": "2025-07-11",
      "close": 88.610992
    },
    {
      "date": "2025-07-14",
      "close": 88.858757
    },
    {
      "date": "2025-07-15",
      "close": 87.639755
    },
    {
      "date": "2025-07-16",
      "close": 88.244293
    },
    {
      "date": "2025-07-17",
      "close": 89.146172
    },
    {
      "date": "2025-07-18",
      "close": 88.57135
    },
    {
      "date": "2025-07-21",
      "close": 88.442513
    },
    {
      "date": "2025-07-22",
      "close": 88.135284
    },
    {
      "date": "2025-07-23",
      "close": 87.491089
    },
    {
      "date": "2025-07-24",
      "close": 92.664436
    },
    {
      "date": "2025-07-25",
      "close": 93.992462
    },
    {
      "date": "2025-07-28",
      "close": 94.289795
    },
    {
      "date": "2025-07-29",
      "close": 94.973625
    },
    {
      "date": "2025-07-30",
      "close": 95.132187
    },
    {
      "date": "2025-07-31",
      "close": 95.36013
    },
    {
      "date": "2025-08-01",
      "close": 94.319519
    },
    {
      "date": "2025-08-04",
      "close": 96.043968
    },
    {
      "date": "2025-08-05",
      "close": 95.479057
    },
    {
      "date": "2025-08-06",
      "close": 95.69709
    },
    {
      "date": "2025-08-07",
      "close": 95.588081
    },
    {
      "date": "2025-08-08",
      "close": 95.984497
    },
    {
      "date": "2025-08-11",
      "close": 96.0737
    },
    {
      "date": "2025-08-12",
      "close": 95.270935
    },
    {
      "date": "2025-08-13",
      "close": 94.715942
    },
    {
      "date": "2025-08-14",
      "close": 94.54747
    },
    {
      "date": "2025-08-15",
      "close": 93.8339
    },
    {
      "date": "2025-08-18",
      "close": 93.496933
    },
    {
      "date": "2025-08-19",
      "close": 92.991493
    },
    {
      "date": "2025-08-20",
      "close": 93.655502
    },
    {
      "date": "2025-08-21",
      "close": 93.120331
    },
    {
      "date": "2025-08-22",
      "close": 93.903267
    },
    {
      "date": "2025-08-25",
      "close": 93.477112
    },
    {
      "date": "2025-08-26",
      "close": 94.051933
    },
    {
      "date": "2025-08-27",
      "close": 93.992462
    },
    {
      "date": "2025-08-28",
      "close": 94.388885
    },
    {
      "date": "2025-08-29",
      "close": 93.893356
    },
    {
      "date": "2025-09-02",
      "close": 92.753632
    },
    {
      "date": "2025-09-03",
      "close": 92.93203
    },
    {
      "date": "2025-09-04",
      "close": 93.457298
    },
    {
      "date": "2025-09-05",
      "close": 92.644623
    },
    {
      "date": "2025-09-08",
      "close": 94.141121
    },
    {
      "date": "2025-09-09",
      "close": 94.032104
    },
    {
      "date": "2025-09-10",
      "close": 93.814079
    },
    {
      "date": "2025-09-11",
      "close": 95.02317
    },
    {
      "date": "2025-09-12",
      "close": 93.37336
    },
    {
      "date": "2025-09-15",
      "close": 92.290054
    },
    {
      "date": "2025-09-16",
      "close": 91.972023
    },
    {
      "date": "2025-09-17",
      "close": 92.52858
    },
    {
      "date": "2025-09-18",
      "close": 88.324547
    },
    {
      "date": "2025-09-19",
      "close": 89.020248
    },
    {
      "date": "2025-09-22",
      "close": 89.378036
    },
    {
      "date": "2025-09-23",
      "close": 87.897186
    },
    {
      "date": "2025-09-24",
      "close": 86.615097
    },
    {
      "date": "2025-09-25",
      "close": 86.197678
    },
    {
      "date": "2025-09-26",
      "close": 86.972893
    },
    {
      "date": "2025-09-29",
      "close": 88.165527
    },
    {
      "date": "2025-09-30",
      "close": 87.90712
    },
    {
      "date": "2025-10-01",
      "close": 86.376572
    },
    {
      "date": "2025-10-02",
      "close": 86.803932
    },
    {
      "date": "2025-10-03",
      "close": 87.072273
    },
    {
      "date": "2025-10-06",
      "close": 87.62883
    },
    {
      "date": "2025-10-07",
      "close": 87.897186
    },
    {
      "date": "2025-10-08",
      "close": 89.318405
    },
    {
      "date": "2025-10-09",
      "close": 90.839012
    },
    {
      "date": "2025-10-10",
      "close": 88.354355
    },
    {
      "date": "2025-10-13",
      "close": 88.841347
    },
    {
      "date": "2025-10-14",
      "close": 88.990433
    },
    {
      "date": "2025-10-15",
      "close": 89.069939
    },
    {
      "date": "2025-10-16",
      "close": 87.400253
    },
    {
      "date": "2025-10-17",
      "close": 88.046257
    },
    {
      "date": "2025-10-20",
      "close": 88.314606
    },
    {
      "date": "2025-10-21",
      "close": 89.775581
    },
    {
      "date": "2025-10-22",
      "close": 86.883438
    },
    {
      "date": "2025-10-23",
      "close": 88.274849
    },
    {
      "date": "2025-10-24",
      "close": 87.897186
    },
    {
      "date": "2025-10-27",
      "close": 88.235092
    },
    {
      "date": "2025-10-28",
      "close": 87.420128
    },
    {
      "date": "2025-10-29",
      "close": 84.895714
    },
    {
      "date": "2025-10-30",
      "close": 85.134247
    },
    {
      "date": "2025-10-31",
      "close": 84.965286
    },
    {
      "date": "2025-11-03",
      "close": 85.859764
    },
    {
      "date": "2025-11-04",
      "close": 85.342957
    },
    {
      "date": "2025-11-05",
      "close": 85.034851
    },
    {
      "date": "2025-11-06",
      "close": 85.660995
    },
    {
      "date": "2025-11-07",
      "close": 86.704544
    },
    {
      "date": "2025-11-10",
      "close": 87.280991
    },
    {
      "date": "2025-11-11",
      "close": 87.290932
    },
    {
      "date": "2025-11-12",
      "close": 88.225151
    },
    {
      "date": "2025-11-13",
      "close": 86.893387
    },
    {
      "date": "2025-11-14",
      "close": 86.545532
    },
    {
      "date": "2025-11-17",
      "close": 85.173996
    },
    {
      "date": "2025-11-18",
      "close": 85.014977
    },
    {
      "date": "2025-11-19",
      "close": 85.492027
    },
    {
      "date": "2025-11-20",
      "close": 86.456078
    },
    {
      "date": "2025-11-21",
      "close": 87.121971
    },
    {
      "date": "2025-11-24",
      "close": 87.897186
    },
    {
      "date": "2025-11-25",
      "close": 88.59288
    },
    {
      "date": "2025-11-26",
      "close": 89.427734
    },
    {
      "date": "2025-11-28",
      "close": 90.361961
    },
    {
      "date": "2025-12-01",
      "close": 88.811531
    },
    {
      "date": "2025-12-02",
      "close": 87.966751
    },
    {
      "date": "2025-12-03",
      "close": 87.777916
    },
    {
      "date": "2025-12-04",
      "close": 89.735832
    },
    {
      "date": "2025-12-05",
      "close": 89.935196
    },
    {
      "date": "2025-12-08",
      "close": 89.516525
    },
    {
      "date": "2025-12-09",
      "close": 90.433617
    },
    {
      "date": "2025-12-10",
      "close": 91.629829
    },
    {
      "date": "2025-12-11",
      "close": 93.553734
    },
    {
      "date": "2025-12-12",
      "close": 93.27462
    },
    {
      "date": "2025-12-15",
      "close": 92.636642
    },
    {
      "date": "2025-12-16",
      "close": 92.636642
    },
    {
      "date": "2025-12-17",
      "close": 93.414177
    },
    {
      "date": "2025-12-18",
      "close": 94.411018
    },
    {
      "date": "2025-12-19",
      "close": 95.058968
    },
    {
      "date": "2025-12-22",
      "close": 97.152336
    },
    {
      "date": "2025-12-23",
      "close": 97.700607
    },
    {
      "date": "2025-12-24",
      "close": 98.328613
    },
    {
      "date": "2025-12-26",
      "close": 99.036369
    },
    {
      "date": "2025-12-29",
      "close": 98.557892
    },
    {
      "date": "2025-12-30",
      "close": 97.870064
    },
    {
      "date": "2025-12-31",
      "close": 96.82338
    },
    {
      "date": "2026-01-02",
      "close": 96.354866
    },
    {
      "date": "2026-01-05",
      "close": 98.139214
    },
    {
      "date": "2026-01-06",
      "close": 100.372147
    },
    {
      "date": "2026-01-07",
      "close": 100.083061
    },
    {
      "date": "2026-01-08",
      "close": 99.42514
    },
    {
      "date": "2026-01-09",
      "close": 97.929878
    },
    {
      "date": "2026-01-12",
      "close": 99.106148
    },
    {
      "date": "2026-01-13",
      "close": 98.577827
    },
    {
      "date": "2026-01-14",
      "close": 99.754097
    },
    {
      "date": "2026-01-15",
      "close": 100.013283
    },
    {
      "date": "2026-01-16",
      "close": 100.661232
    },
    {
      "date": "2026-01-20",
      "close": 97.102501
    },
    {
      "date": "2026-01-21",
      "close": 98.46817
    },
    {
      "date": "2026-01-22",
      "close": 98.46817
    },
    {
      "date": "2026-01-23",
      "close": 97.740479
    },
    {
      "date": "2026-01-26",
      "close": 98.577827
    },
    {
      "date": "2026-01-27",
      "close": 98.189056
    },
    {
      "date": "2026-01-28",
      "close": 98.398392
    },
    {
      "date": "2026-01-29",
      "close": 97.78035
    },
    {
      "date": "2026-01-30",
      "close": 96.584137
    },
    {
      "date": "2026-02-02",
      "close": 96.504387
    },
    {
      "date": "2026-02-03",
      "close": 87.433121
    },
    {
      "date": "2026-02-04",
      "close": 88.210655
    },
    {
      "date": "2026-02-05",
      "close": 85.240067
    },
    {
      "date": "2026-02-06",
      "close": 84.56221
    },
    {
      "date": "2026-02-09",
      "close": 86.027573
    },
    {
      "date": "2026-02-10",
      "close": 82.249535
    },
    {
      "date": "2026-02-11",
      "close": 80.16613
    },
    {
      "date": "2026-02-12",
      "close": 78.760582
    },
    {
      "date": "2026-02-13",
      "close": 79.219131
    },
    {
      "date": "2026-02-17",
      "close": 79.986694
    },
    {
      "date": "2026-02-18",
      "close": 81.870728
    },
    {
      "date": "2026-02-19",
      "close": 81.153008
    },
    {
      "date": "2026-02-20",
      "close": 81.611557
    },
    {
      "date": "2026-02-23",
      "close": 79.667709
    },
    {
      "date": "2026-02-24",
      "close": 80.853951
    },
    {
      "date": "2026-02-25",
      "close": 83.724861
    },
    {
      "date": "2026-02-26",
      "close": 88.310341
    },
    {
      "date": "2026-02-27",
      "close": 87.303528
    },
    {
      "date": "2026-03-02",
      "close": 87.811913
    },
    {
      "date": "2026-03-03",
      "close": 87.144035
    },
    {
      "date": "2026-03-04",
      "close": 88.848633
    },
    {
      "date": "2026-03-05",
      "close": 87.991348
    },
    {
      "date": "2026-03-06",
      "close": 88.150848
    },
    {
      "date": "2026-03-09",
      "close": 87.772049
    },
    {
      "date": "2026-03-10",
      "close": 87.323463
    },
    {
      "date": "2026-03-11",
      "close": 85.230095
    },
    {
      "date": "2026-03-12",
      "close": 83.79464
    },
    {
      "date": "2026-03-13",
      "close": 85.260002
    },
    {
      "date": "2026-03-16",
      "close": 85.849998
    },
    {
      "date": "2026-03-17",
      "close": 86.470001
    },
    {
      "date": "2026-03-18",
      "close": 85.440002
    },
    {
      "date": "2026-03-19",
      "close": 86.269997
    },
    {
      "date": "2026-03-20",
      "close": 86.339996
    },
    {
      "date": "2026-03-23",
      "close": 86.400002
    },
    {
      "date": "2026-03-24",
      "close": 84.279999
    },
    {
      "date": "2026-03-25",
      "close": 83.739998
    },
    {
      "date": "2026-03-26",
      "close": 83.779999
    },
    {
      "date": "2026-03-27",
      "close": 81.480003
    },
    {
      "date": "2026-03-30",
      "close": 83.519997
    },
    {
      "date": "2026-03-31",
      "close": 84.889999
    },
    {
      "date": "2026-04-01",
      "close": 85.150002
    },
    {
      "date": "2026-04-02",
      "close": 86.650002
    },
    {
      "date": "2026-04-06",
      "close": 87.900002
    },
    {
      "date": "2026-04-07",
      "close": 86.400002
    },
    {
      "date": "2026-04-08",
      "close": 88.089996
    },
    {
      "date": "2026-04-09",
      "close": 84.209999
    },
    {
      "date": "2026-04-10",
      "close": 83.160004
    },
    {
      "date": "2026-04-13",
      "close": 86.150002
    },
    {
      "date": "2026-04-14",
      "close": 86.709999
    },
    {
      "date": "2026-04-15",
      "close": 88.550003
    },
    {
      "date": "2026-04-16",
      "close": 88.870003
    },
    {
      "date": "2026-04-17",
      "close": 88.610001
    },
    {
      "date": "2026-04-20",
      "close": 87.779999
    },
    {
      "date": "2026-04-21",
      "close": 87.599998
    },
    {
      "date": "2026-04-22",
      "close": 86.370003
    },
    {
      "date": "2026-04-23",
      "close": 87.040001
    },
    {
      "date": "2026-04-24",
      "close": 89.900002
    },
    {
      "date": "2026-04-27",
      "close": 90.43
    },
    {
      "date": "2026-04-28",
      "close": 91.309998
    },
    {
      "date": "2026-04-29",
      "close": 91.269997
    },
    {
      "date": "2026-04-30",
      "close": 91.910004
    },
    {
      "date": "2026-05-01",
      "close": 91.32
    },
    {
      "date": "2026-05-04",
      "close": 91.300003
    },
    {
      "date": "2026-05-05",
      "close": 89
    },
    {
      "date": "2026-05-06",
      "close": 89.199997
    },
    {
      "date": "2026-05-07",
      "close": 89
    },
    {
      "date": "2026-05-08",
      "close": 88.910004
    },
    {
      "date": "2026-05-11",
      "close": 88.480003
    }
  ]
}
