{
  "ticker": "RF",
  "source": "https://query2.finance.yahoo.com/v8/finance/chart/RF?range=2y&interval=1d&events=history",
  "fetchedAt": "2026-06-19T01:16:34.464Z",
  "bars": [
    {
      "date": "2024-06-20",
      "close": 17.429255
    },
    {
      "date": "2024-06-21",
      "close": 17.447689
    },
    {
      "date": "2024-06-24",
      "close": 17.797932
    },
    {
      "date": "2024-06-25",
      "close": 17.530643
    },
    {
      "date": "2024-06-26",
      "close": 17.401606
    },
    {
      "date": "2024-06-27",
      "close": 17.696547
    },
    {
      "date": "2024-06-28",
      "close": 18.470774
    },
    {
      "date": "2024-07-01",
      "close": 18.341732
    },
    {
      "date": "2024-07-02",
      "close": 18.516857
    },
    {
      "date": "2024-07-03",
      "close": 18.332514
    },
    {
      "date": "2024-07-05",
      "close": 17.982273
    },
    {
      "date": "2024-07-08",
      "close": 18.240349
    },
    {
      "date": "2024-07-09",
      "close": 18.535292
    },
    {
      "date": "2024-07-10",
      "close": 18.609028
    },
    {
      "date": "2024-07-11",
      "close": 19.088308
    },
    {
      "date": "2024-07-12",
      "close": 18.867098
    },
    {
      "date": "2024-07-15",
      "close": 19.3556
    },
    {
      "date": "2024-07-16",
      "close": 20.065306
    },
    {
      "date": "2024-07-17",
      "close": 20.378681
    },
    {
      "date": "2024-07-18",
      "close": 20.360247
    },
    {
      "date": "2024-07-19",
      "close": 20.360247
    },
    {
      "date": "2024-07-22",
      "close": 20.636755
    },
    {
      "date": "2024-07-23",
      "close": 20.636755
    },
    {
      "date": "2024-07-24",
      "close": 20.378681
    },
    {
      "date": "2024-07-25",
      "close": 20.784225
    },
    {
      "date": "2024-07-26",
      "close": 20.977783
    },
    {
      "date": "2024-07-29",
      "close": 20.673624
    },
    {
      "date": "2024-07-30",
      "close": 20.95013
    },
    {
      "date": "2024-07-31",
      "close": 20.61832
    },
    {
      "date": "2024-08-01",
      "close": 19.853317
    },
    {
      "date": "2024-08-02",
      "close": 19.244997
    },
    {
      "date": "2024-08-05",
      "close": 18.811798
    },
    {
      "date": "2024-08-06",
      "close": 19.069872
    },
    {
      "date": "2024-08-07",
      "close": 18.885534
    },
    {
      "date": "2024-08-08",
      "close": 19.198912
    },
    {
      "date": "2024-08-09",
      "close": 19.106741
    },
    {
      "date": "2024-08-12",
      "close": 19.125174
    },
    {
      "date": "2024-08-13",
      "close": 19.254211
    },
    {
      "date": "2024-08-14",
      "close": 19.254211
    },
    {
      "date": "2024-08-15",
      "close": 19.47542
    },
    {
      "date": "2024-08-16",
      "close": 19.816444
    },
    {
      "date": "2024-08-19",
      "close": 20.056087
    },
    {
      "date": "2024-08-20",
      "close": 20.129824
    },
    {
      "date": "2024-08-21",
      "close": 20.083738
    },
    {
      "date": "2024-08-22",
      "close": 20.424765
    },
    {
      "date": "2024-08-23",
      "close": 21.023869
    },
    {
      "date": "2024-08-26",
      "close": 21.005438
    },
    {
      "date": "2024-08-27",
      "close": 20.977783
    },
    {
      "date": "2024-08-28",
      "close": 21.180553
    },
    {
      "date": "2024-08-29",
      "close": 21.392548
    },
    {
      "date": "2024-08-30",
      "close": 21.586102
    },
    {
      "date": "2024-09-03",
      "close": 21.427723
    },
    {
      "date": "2024-09-04",
      "close": 21.269344
    },
    {
      "date": "2024-09-05",
      "close": 21.064384
    },
    {
      "date": "2024-09-06",
      "close": 20.654463
    },
    {
      "date": "2024-09-09",
      "close": 21.008484
    },
    {
      "date": "2024-09-10",
      "close": 20.794207
    },
    {
      "date": "2024-09-11",
      "close": 20.496082
    },
    {
      "date": "2024-09-12",
      "close": 20.430868
    },
    {
      "date": "2024-09-13",
      "close": 20.468132
    },
    {
      "date": "2024-09-16",
      "close": 20.775576
    },
    {
      "date": "2024-09-17",
      "close": 20.989853
    },
    {
      "date": "2024-09-18",
      "close": 21.166862
    },
    {
      "date": "2024-09-19",
      "close": 21.763115
    },
    {
      "date": "2024-09-20",
      "close": 21.530205
    },
    {
      "date": "2024-09-23",
      "close": 21.343872
    },
    {
      "date": "2024-09-24",
      "close": 21.353191
    },
    {
      "date": "2024-09-25",
      "close": 20.999168
    },
    {
      "date": "2024-09-26",
      "close": 21.334558
    },
    {
      "date": "2024-09-27",
      "close": 21.455673
    },
    {
      "date": "2024-09-30",
      "close": 21.735163
    },
    {
      "date": "2024-10-01",
      "close": 20.999168
    },
    {
      "date": "2024-10-02",
      "close": 21.017801
    },
    {
      "date": "2024-10-03",
      "close": 20.896688
    },
    {
      "date": "2024-10-04",
      "close": 21.278658
    },
    {
      "date": "2024-10-07",
      "close": 21.250711
    },
    {
      "date": "2024-10-08",
      "close": 21.185497
    },
    {
      "date": "2024-10-09",
      "close": 21.502253
    },
    {
      "date": "2024-10-10",
      "close": 21.464989
    },
    {
      "date": "2024-10-11",
      "close": 22.070555
    },
    {
      "date": "2024-10-14",
      "close": 22.219616
    },
    {
      "date": "2024-10-15",
      "close": 22.135771
    },
    {
      "date": "2024-10-16",
      "close": 22.340731
    },
    {
      "date": "2024-10-17",
      "close": 22.340731
    },
    {
      "date": "2024-10-18",
      "close": 22.191668
    },
    {
      "date": "2024-10-21",
      "close": 22.014654
    },
    {
      "date": "2024-10-22",
      "close": 22.02397
    },
    {
      "date": "2024-10-23",
      "close": 22.02397
    },
    {
      "date": "2024-10-24",
      "close": 22.135771
    },
    {
      "date": "2024-10-25",
      "close": 21.893543
    },
    {
      "date": "2024-10-28",
      "close": 22.41526
    },
    {
      "date": "2024-10-29",
      "close": 22.238251
    },
    {
      "date": "2024-10-30",
      "close": 22.41526
    },
    {
      "date": "2024-10-31",
      "close": 22.238251
    },
    {
      "date": "2024-11-01",
      "close": 21.94944
    },
    {
      "date": "2024-11-04",
      "close": 21.791061
    },
    {
      "date": "2024-11-05",
      "close": 22.005342
    },
    {
      "date": "2024-11-06",
      "close": 24.511452
    },
    {
      "date": "2024-11-07",
      "close": 23.672974
    },
    {
      "date": "2024-11-08",
      "close": 23.868622
    },
    {
      "date": "2024-11-11",
      "close": 24.408974
    },
    {
      "date": "2024-11-12",
      "close": 24.390337
    },
    {
      "date": "2024-11-13",
      "close": 24.315807
    },
    {
      "date": "2024-11-14",
      "close": 24.474186
    },
    {
      "date": "2024-11-15",
      "close": 24.558033
    },
    {
      "date": "2024-11-18",
      "close": 24.530085
    },
    {
      "date": "2024-11-19",
      "close": 24.46487
    },
    {
      "date": "2024-11-20",
      "close": 24.46487
    },
    {
      "date": "2024-11-21",
      "close": 24.912058
    },
    {
      "date": "2024-11-22",
      "close": 25.415142
    },
    {
      "date": "2024-11-25",
      "close": 25.592155
    },
    {
      "date": "2024-11-26",
      "close": 25.443089
    },
    {
      "date": "2024-11-27",
      "close": 25.387194
    },
    {
      "date": "2024-11-29",
      "close": 25.396509
    },
    {
      "date": "2024-12-02",
      "close": 24.945185
    },
    {
      "date": "2024-12-03",
      "close": 24.766535
    },
    {
      "date": "2024-12-04",
      "close": 24.728922
    },
    {
      "date": "2024-12-05",
      "close": 24.719522
    },
    {
      "date": "2024-12-06",
      "close": 24.691313
    },
    {
      "date": "2024-12-09",
      "close": 24.192976
    },
    {
      "date": "2024-12-10",
      "close": 23.816868
    },
    {
      "date": "2024-12-11",
      "close": 23.882685
    },
    {
      "date": "2024-12-12",
      "close": 23.553595
    },
    {
      "date": "2024-12-13",
      "close": 23.610012
    },
    {
      "date": "2024-12-16",
      "close": 23.675831
    },
    {
      "date": "2024-12-17",
      "close": 23.139879
    },
    {
      "date": "2024-12-18",
      "close": 21.898733
    },
    {
      "date": "2024-12-19",
      "close": 21.785898
    },
    {
      "date": "2024-12-20",
      "close": 22.350056
    },
    {
      "date": "2024-12-23",
      "close": 22.415874
    },
    {
      "date": "2024-12-24",
      "close": 22.585125
    },
    {
      "date": "2024-12-26",
      "close": 22.556915
    },
    {
      "date": "2024-12-27",
      "close": 22.321848
    },
    {
      "date": "2024-12-30",
      "close": 22.246628
    },
    {
      "date": "2024-12-31",
      "close": 22.114992
    },
    {
      "date": "2025-01-02",
      "close": 21.870522
    },
    {
      "date": "2025-01-03",
      "close": 22.209019
    },
    {
      "date": "2025-01-06",
      "close": 22.359459
    },
    {
      "date": "2025-01-07",
      "close": 22.425278
    },
    {
      "date": "2025-01-08",
      "close": 22.39707
    },
    {
      "date": "2025-01-10",
      "close": 21.682468
    },
    {
      "date": "2025-01-13",
      "close": 22.209019
    },
    {
      "date": "2025-01-14",
      "close": 22.566319
    },
    {
      "date": "2025-01-15",
      "close": 23.224501
    },
    {
      "date": "2025-01-16",
      "close": 23.055256
    },
    {
      "date": "2025-01-17",
      "close": 22.754372
    },
    {
      "date": "2025-01-21",
      "close": 23.177488
    },
    {
      "date": "2025-01-22",
      "close": 22.867201
    },
    {
      "date": "2025-01-23",
      "close": 22.810783
    },
    {
      "date": "2025-01-24",
      "close": 23.00824
    },
    {
      "date": "2025-01-27",
      "close": 23.290319
    },
    {
      "date": "2025-01-28",
      "close": 23.271515
    },
    {
      "date": "2025-01-29",
      "close": 23.11167
    },
    {
      "date": "2025-01-30",
      "close": 23.290319
    },
    {
      "date": "2025-01-31",
      "close": 23.168087
    },
    {
      "date": "2025-02-03",
      "close": 22.613333
    },
    {
      "date": "2025-02-04",
      "close": 22.904814
    },
    {
      "date": "2025-02-05",
      "close": 22.867201
    },
    {
      "date": "2025-02-06",
      "close": 23.168087
    },
    {
      "date": "2025-02-07",
      "close": 22.989437
    },
    {
      "date": "2025-02-10",
      "close": 22.641537
    },
    {
      "date": "2025-02-11",
      "close": 22.93302
    },
    {
      "date": "2025-02-12",
      "close": 22.556915
    },
    {
      "date": "2025-02-13",
      "close": 22.613333
    },
    {
      "date": "2025-02-14",
      "close": 22.867201
    },
    {
      "date": "2025-02-18",
      "close": 23.18689
    },
    {
      "date": "2025-02-19",
      "close": 23.055256
    },
    {
      "date": "2025-02-20",
      "close": 22.622732
    },
    {
      "date": "2025-02-21",
      "close": 21.992754
    },
    {
      "date": "2025-02-24",
      "close": 22.03977
    },
    {
      "date": "2025-02-25",
      "close": 21.973951
    },
    {
      "date": "2025-02-26",
      "close": 21.983355
    },
    {
      "date": "2025-02-27",
      "close": 22.002159
    },
    {
      "date": "2025-02-28",
      "close": 22.293638
    },
    {
      "date": "2025-03-03",
      "close": 21.989552
    },
    {
      "date": "2025-03-04",
      "close": 21.248331
    },
    {
      "date": "2025-03-05",
      "close": 20.991753
    },
    {
      "date": "2025-03-06",
      "close": 20.858713
    },
    {
      "date": "2025-03-07",
      "close": 20.972748
    },
    {
      "date": "2025-03-10",
      "close": 20.459593
    },
    {
      "date": "2025-03-11",
      "close": 19.946442
    },
    {
      "date": "2025-03-12",
      "close": 20.01296
    },
    {
      "date": "2025-03-13",
      "close": 19.8039
    },
    {
      "date": "2025-03-14",
      "close": 20.364569
    },
    {
      "date": "2025-03-17",
      "close": 20.469099
    },
    {
      "date": "2025-03-18",
      "close": 20.412081
    },
    {
      "date": "2025-03-19",
      "close": 20.668657
    },
    {
      "date": "2025-03-20",
      "close": 20.602139
    },
    {
      "date": "2025-03-21",
      "close": 20.630644
    },
    {
      "date": "2025-03-24",
      "close": 21.162806
    },
    {
      "date": "2025-03-25",
      "close": 21.305346
    },
    {
      "date": "2025-03-26",
      "close": 21.134295
    },
    {
      "date": "2025-03-27",
      "close": 20.839708
    },
    {
      "date": "2025-03-28",
      "close": 20.355061
    },
    {
      "date": "2025-03-31",
      "close": 20.649651
    },
    {
      "date": "2025-04-01",
      "close": 20.497608
    },
    {
      "date": "2025-04-02",
      "close": 20.925234
    },
    {
      "date": "2025-04-03",
      "close": 18.635054
    },
    {
      "date": "2025-04-04",
      "close": 17.732285
    },
    {
      "date": "2025-04-07",
      "close": 17.751287
    },
    {
      "date": "2025-04-08",
      "close": 17.428192
    },
    {
      "date": "2025-04-09",
      "close": 19.005661
    },
    {
      "date": "2025-04-10",
      "close": 18.055378
    },
    {
      "date": "2025-04-11",
      "close": 18.026871
    },
    {
      "date": "2025-04-14",
      "close": 18.311954
    },
    {
      "date": "2025-04-15",
      "close": 18.464001
    },
    {
      "date": "2025-04-16",
      "close": 18.216927
    },
    {
      "date": "2025-04-17",
      "close": 18.349964
    },
    {
      "date": "2025-04-21",
      "close": 18.140903
    },
    {
      "date": "2025-04-22",
      "close": 18.796597
    },
    {
      "date": "2025-04-23",
      "close": 19.024668
    },
    {
      "date": "2025-04-24",
      "close": 19.518816
    },
    {
      "date": "2025-04-25",
      "close": 19.27174
    },
    {
      "date": "2025-04-28",
      "close": 19.442791
    },
    {
      "date": "2025-04-29",
      "close": 19.499811
    },
    {
      "date": "2025-04-30",
      "close": 19.395279
    },
    {
      "date": "2025-05-01",
      "close": 19.490303
    },
    {
      "date": "2025-05-02",
      "close": 20.003458
    },
    {
      "date": "2025-05-05",
      "close": 20.060476
    },
    {
      "date": "2025-05-06",
      "close": 19.680363
    },
    {
      "date": "2025-05-07",
      "close": 19.746881
    },
    {
      "date": "2025-05-08",
      "close": 20.24103
    },
    {
      "date": "2025-05-09",
      "close": 20.10799
    },
    {
      "date": "2025-05-12",
      "close": 21.143799
    },
    {
      "date": "2025-05-13",
      "close": 21.32435
    },
    {
      "date": "2025-05-14",
      "close": 21.32435
    },
    {
      "date": "2025-05-15",
      "close": 21.343357
    },
    {
      "date": "2025-05-16",
      "close": 21.466896
    },
    {
      "date": "2025-05-19",
      "close": 21.419382
    },
    {
      "date": "2025-05-20",
      "close": 21.143799
    },
    {
      "date": "2025-05-21",
      "close": 20.260036
    },
    {
      "date": "2025-05-22",
      "close": 20.307549
    },
    {
      "date": "2025-05-23",
      "close": 20.184011
    },
    {
      "date": "2025-05-27",
      "close": 20.592634
    },
    {
      "date": "2025-05-28",
      "close": 20.269537
    },
    {
      "date": "2025-05-29",
      "close": 20.497608
    },
    {
      "date": "2025-05-30",
      "close": 20.374069
    },
    {
      "date": "2025-06-02",
      "close": 20.29715
    },
    {
      "date": "2025-06-03",
      "close": 20.700975
    },
    {
      "date": "2025-06-04",
      "close": 20.479834
    },
    {
      "date": "2025-06-05",
      "close": 20.499065
    },
    {
      "date": "2025-06-06",
      "close": 21.200956
    },
    {
      "date": "2025-06-09",
      "close": 21.239414
    },
    {
      "date": "2025-06-10",
      "close": 21.49902
    },
    {
      "date": "2025-06-11",
      "close": 21.431715
    },
    {
      "date": "2025-06-12",
      "close": 21.229799
    },
    {
      "date": "2025-06-13",
      "close": 20.681747
    },
    {
      "date": "2025-06-16",
      "close": 20.845203
    },
    {
      "date": "2025-06-17",
      "close": 20.710594
    },
    {
      "date": "2025-06-18",
      "close": 21.11442
    },
    {
      "date": "2025-06-20",
      "close": 21.345179
    },
    {
      "date": "2025-06-23",
      "close": 21.768236
    },
    {
      "date": "2025-06-24",
      "close": 21.998993
    },
    {
      "date": "2025-06-25",
      "close": 22.008612
    },
    {
      "date": "2025-06-26",
      "close": 22.450895
    },
    {
      "date": "2025-06-27",
      "close": 22.450895
    },
    {
      "date": "2025-06-30",
      "close": 22.614351
    },
    {
      "date": "2025-07-01",
      "close": 23.239323
    },
    {
      "date": "2025-07-02",
      "close": 23.604689
    },
    {
      "date": "2025-07-03",
      "close": 23.845064
    },
    {
      "date": "2025-07-07",
      "close": 23.62392
    },
    {
      "date": "2025-07-08",
      "close": 23.710455
    },
    {
      "date": "2025-07-09",
      "close": 23.68161
    },
    {
      "date": "2025-07-10",
      "close": 23.883526
    },
    {
      "date": "2025-07-11",
      "close": 23.7393
    },
    {
      "date": "2025-07-14",
      "close": 23.748915
    },
    {
      "date": "2025-07-15",
      "close": 23.104713
    },
    {
      "date": "2025-07-16",
      "close": 23.152786
    },
    {
      "date": "2025-07-17",
      "close": 23.566231
    },
    {
      "date": "2025-07-18",
      "close": 25.008471
    },
    {
      "date": "2025-07-21",
      "close": 25.046934
    },
    {
      "date": "2025-07-22",
      "close": 25.191158
    },
    {
      "date": "2025-07-23",
      "close": 25.35461
    },
    {
      "date": "2025-07-24",
      "close": 25.287306
    },
    {
      "date": "2025-07-25",
      "close": 25.402687
    },
    {
      "date": "2025-07-28",
      "close": 25.287306
    },
    {
      "date": "2025-07-29",
      "close": 25.18154
    },
    {
      "date": "2025-07-30",
      "close": 24.710409
    },
    {
      "date": "2025-07-31",
      "close": 24.354658
    },
    {
      "date": "2025-08-01",
      "close": 23.931601
    },
    {
      "date": "2025-08-04",
      "close": 24.210434
    },
    {
      "date": "2025-08-05",
      "close": 24.210434
    },
    {
      "date": "2025-08-06",
      "close": 23.97006
    },
    {
      "date": "2025-08-07",
      "close": 23.691227
    },
    {
      "date": "2025-08-08",
      "close": 23.960443
    },
    {
      "date": "2025-08-11",
      "close": 23.68161
    },
    {
      "date": "2025-08-12",
      "close": 24.354658
    },
    {
      "date": "2025-08-13",
      "close": 24.84502
    },
    {
      "date": "2025-08-14",
      "close": 25.046934
    },
    {
      "date": "2025-08-15",
      "close": 24.61426
    },
    {
      "date": "2025-08-18",
      "close": 24.700796
    },
    {
      "date": "2025-08-19",
      "close": 24.729637
    },
    {
      "date": "2025-08-20",
      "close": 24.86425
    },
    {
      "date": "2025-08-21",
      "close": 24.748869
    },
    {
      "date": "2025-08-22",
      "close": 25.729593
    },
    {
      "date": "2025-08-25",
      "close": 25.623829
    },
    {
      "date": "2025-08-26",
      "close": 26.037273
    },
    {
      "date": "2025-08-27",
      "close": 26.354565
    },
    {
      "date": "2025-08-28",
      "close": 26.277645
    },
    {
      "date": "2025-08-29",
      "close": 26.335335
    },
    {
      "date": "2025-09-02",
      "close": 26.107176
    },
    {
      "date": "2025-09-03",
      "close": 26.155722
    },
    {
      "date": "2025-09-04",
      "close": 26.563496
    },
    {
      "date": "2025-09-05",
      "close": 26.243103
    },
    {
      "date": "2025-09-08",
      "close": 26.252811
    },
    {
      "date": "2025-09-09",
      "close": 26.039215
    },
    {
      "date": "2025-09-10",
      "close": 26.252811
    },
    {
      "date": "2025-09-11",
      "close": 26.252811
    },
    {
      "date": "2025-09-12",
      "close": 26.369316
    },
    {
      "date": "2025-09-15",
      "close": 26.116886
    },
    {
      "date": "2025-09-16",
      "close": 25.786783
    },
    {
      "date": "2025-09-17",
      "close": 26.146013
    },
    {
      "date": "2025-09-18",
      "close": 26.602331
    },
    {
      "date": "2025-09-19",
      "close": 26.369316
    },
    {
      "date": "2025-09-22",
      "close": 25.786783
    },
    {
      "date": "2025-09-23",
      "close": 25.951834
    },
    {
      "date": "2025-09-24",
      "close": 25.883873
    },
    {
      "date": "2025-09-25",
      "close": 25.825619
    },
    {
      "date": "2025-09-26",
      "close": 25.854746
    },
    {
      "date": "2025-09-29",
      "close": 25.728531
    },
    {
      "date": "2025-09-30",
      "close": 25.602316
    },
    {
      "date": "2025-10-01",
      "close": 25.446972
    },
    {
      "date": "2025-10-02",
      "close": 25.437263
    },
    {
      "date": "2025-10-03",
      "close": 25.621733
    },
    {
      "date": "2025-10-06",
      "close": 25.107164
    },
    {
      "date": "2025-10-07",
      "close": 24.980947
    },
    {
      "date": "2025-10-08",
      "close": 24.553757
    },
    {
      "date": "2025-10-09",
      "close": 24.573175
    },
    {
      "date": "2025-10-10",
      "close": 23.456654
    },
    {
      "date": "2025-10-13",
      "close": 23.845009
    },
    {
      "date": "2025-10-14",
      "close": 24.42754
    },
    {
      "date": "2025-10-15",
      "close": 24.019768
    },
    {
      "date": "2025-10-16",
      "close": 22.670235
    },
    {
      "date": "2025-10-17",
      "close": 22.893538
    },
    {
      "date": "2025-10-20",
      "close": 23.359564
    },
    {
      "date": "2025-10-21",
      "close": 23.650829
    },
    {
      "date": "2025-10-22",
      "close": 23.408108
    },
    {
      "date": "2025-10-23",
      "close": 23.398399
    },
    {
      "date": "2025-10-24",
      "close": 23.854717
    },
    {
      "date": "2025-10-27",
      "close": 23.534323
    },
    {
      "date": "2025-10-28",
      "close": 23.563452
    },
    {
      "date": "2025-10-29",
      "close": 23.369274
    },
    {
      "date": "2025-10-30",
      "close": 23.495489
    },
    {
      "date": "2025-10-31",
      "close": 23.495489
    },
    {
      "date": "2025-11-03",
      "close": 23.534323
    },
    {
      "date": "2025-11-04",
      "close": 23.446945
    },
    {
      "date": "2025-11-05",
      "close": 23.670246
    },
    {
      "date": "2025-11-06",
      "close": 23.602285
    },
    {
      "date": "2025-11-07",
      "close": 24.126566
    },
    {
      "date": "2025-11-10",
      "close": 24.311035
    },
    {
      "date": "2025-11-11",
      "close": 24.330452
    },
    {
      "date": "2025-11-12",
      "close": 24.650845
    },
    {
      "date": "2025-11-13",
      "close": 24.233362
    },
    {
      "date": "2025-11-14",
      "close": 24.233362
    },
    {
      "date": "2025-11-17",
      "close": 23.592577
    },
    {
      "date": "2025-11-18",
      "close": 23.476072
    },
    {
      "date": "2025-11-19",
      "close": 23.514906
    },
    {
      "date": "2025-11-20",
      "close": 23.398399
    },
    {
      "date": "2025-11-21",
      "close": 24.184818
    },
    {
      "date": "2025-11-24",
      "close": 24.126566
    },
    {
      "date": "2025-11-25",
      "close": 24.679972
    },
    {
      "date": "2025-11-26",
      "close": 24.709101
    },
    {
      "date": "2025-11-28",
      "close": 24.709101
    },
    {
      "date": "2025-12-01",
      "close": 24.851358
    },
    {
      "date": "2025-12-02",
      "close": 24.929846
    },
    {
      "date": "2025-12-03",
      "close": 25.70492
    },
    {
      "date": "2025-12-04",
      "close": 25.91095
    },
    {
      "date": "2025-12-05",
      "close": 25.783407
    },
    {
      "date": "2025-12-08",
      "close": 25.842272
    },
    {
      "date": "2025-12-09",
      "close": 25.940384
    },
    {
      "date": "2025-12-10",
      "close": 26.862619
    },
    {
      "date": "2025-12-11",
      "close": 27.313929
    },
    {
      "date": "2025-12-12",
      "close": 27.078465
    },
    {
      "date": "2025-12-15",
      "close": 26.872433
    },
    {
      "date": "2025-12-16",
      "close": 26.990164
    },
    {
      "date": "2025-12-17",
      "close": 27.04903
    },
    {
      "date": "2025-12-18",
      "close": 26.970541
    },
    {
      "date": "2025-12-19",
      "close": 27.137331
    },
    {
      "date": "2025-12-22",
      "close": 27.294308
    },
    {
      "date": "2025-12-23",
      "close": 27.029409
    },
    {
      "date": "2025-12-24",
      "close": 27.206007
    },
    {
      "date": "2025-12-26",
      "close": 27.264875
    },
    {
      "date": "2025-12-29",
      "close": 27.029409
    },
    {
      "date": "2025-12-30",
      "close": 26.803755
    },
    {
      "date": "2025-12-31",
      "close": 26.587912
    },
    {
      "date": "2026-01-02",
      "close": 27.039219
    },
    {
      "date": "2026-01-05",
      "close": 27.735804
    },
    {
      "date": "2026-01-06",
      "close": 28.167488
    },
    {
      "date": "2026-01-07",
      "close": 27.922213
    },
    {
      "date": "2026-01-08",
      "close": 28.295034
    },
    {
      "date": "2026-01-09",
      "close": 27.981079
    },
    {
      "date": "2026-01-12",
      "close": 27.725992
    },
    {
      "date": "2026-01-13",
      "close": 27.313929
    },
    {
      "date": "2026-01-14",
      "close": 27.608259
    },
    {
      "date": "2026-01-15",
      "close": 27.981079
    },
    {
      "date": "2026-01-16",
      "close": 27.245251
    },
    {
      "date": "2026-01-20",
      "close": 27.107895
    },
    {
      "date": "2026-01-21",
      "close": 28.108622
    },
    {
      "date": "2026-01-22",
      "close": 27.755426
    },
    {
      "date": "2026-01-23",
      "close": 26.960732
    },
    {
      "date": "2026-01-26",
      "close": 27.215818
    },
    {
      "date": "2026-01-27",
      "close": 27.343363
    },
    {
      "date": "2026-01-28",
      "close": 27.333551
    },
    {
      "date": "2026-01-29",
      "close": 27.922213
    },
    {
      "date": "2026-01-30",
      "close": 27.961458
    },
    {
      "date": "2026-02-02",
      "close": 28.569742
    },
    {
      "date": "2026-02-03",
      "close": 29.266325
    },
    {
      "date": "2026-02-04",
      "close": 29.864799
    },
    {
      "date": "2026-02-05",
      "close": 29.923664
    },
    {
      "date": "2026-02-06",
      "close": 30.345541
    },
    {
      "date": "2026-02-09",
      "close": 30.178751
    },
    {
      "date": "2026-02-10",
      "close": 30.237617
    },
    {
      "date": "2026-02-11",
      "close": 30.365162
    },
    {
      "date": "2026-02-12",
      "close": 29.217272
    },
    {
      "date": "2026-02-13",
      "close": 29.178026
    },
    {
      "date": "2026-02-17",
      "close": 29.217272
    },
    {
      "date": "2026-02-18",
      "close": 29.49198
    },
    {
      "date": "2026-02-19",
      "close": 29.158403
    },
    {
      "date": "2026-02-20",
      "close": 29.49198
    },
    {
      "date": "2026-02-23",
      "close": 28.167488
    },
    {
      "date": "2026-02-24",
      "close": 27.902592
    },
    {
      "date": "2026-02-25",
      "close": 28.452009
    },
    {
      "date": "2026-02-26",
      "close": 28.805208
    },
    {
      "date": "2026-02-27",
      "close": 27.304117
    },
    {
      "date": "2026-03-02",
      "close": 27.705284
    },
    {
      "date": "2026-03-03",
      "close": 27.477461
    },
    {
      "date": "2026-03-04",
      "close": 27.56661
    },
    {
      "date": "2026-03-05",
      "close": 27.477461
    },
    {
      "date": "2026-03-06",
      "close": 26.784088
    },
    {
      "date": "2026-03-09",
      "close": 26.704842
    },
    {
      "date": "2026-03-10",
      "close": 26.506737
    },
    {
      "date": "2026-03-11",
      "close": 25.961941
    },
    {
      "date": "2026-03-12",
      "close": 25.080364
    },
    {
      "date": "2026-03-13",
      "close": 24.763393
    },
    {
      "date": "2026-03-16",
      "close": 25.090271
    },
    {
      "date": "2026-03-17",
      "close": 25.209135
    },
    {
      "date": "2026-03-18",
      "close": 24.961502
    },
    {
      "date": "2026-03-19",
      "close": 24.971405
    },
    {
      "date": "2026-03-20",
      "close": 25.119987
    },
    {
      "date": "2026-03-23",
      "close": 25.219038
    },
    {
      "date": "2026-03-24",
      "close": 25.397335
    },
    {
      "date": "2026-03-25",
      "close": 25.516201
    },
    {
      "date": "2026-03-26",
      "close": 25.268566
    },
    {
      "date": "2026-03-27",
      "close": 24.921879
    },
    {
      "date": "2026-03-30",
      "close": 25.001122
    },
    {
      "date": "2026-03-31",
      "close": 25.872795
    },
    {
      "date": "2026-04-01",
      "close": 26.090712
    },
    {
      "date": "2026-04-02",
      "close": 26.219481
    },
    {
      "date": "2026-04-06",
      "close": 26.486925
    },
    {
      "date": "2026-04-07",
      "close": 26.358156
    },
    {
      "date": "2026-04-08",
      "close": 27.210016
    },
    {
      "date": "2026-04-09",
      "close": 27.883581
    },
    {
      "date": "2026-04-10",
      "close": 27.239733
    },
    {
      "date": "2026-04-13",
      "close": 27.56661
    },
    {
      "date": "2026-04-14",
      "close": 27.487366
    },
    {
      "date": "2026-04-15",
      "close": 27.58642
    },
    {
      "date": "2026-04-16",
      "close": 27.655758
    },
    {
      "date": "2026-04-17",
      "close": 27.86377
    },
    {
      "date": "2026-04-20",
      "close": 28.042067
    },
    {
      "date": "2026-04-21",
      "close": 28.081688
    },
    {
      "date": "2026-04-22",
      "close": 27.943012
    },
    {
      "date": "2026-04-23",
      "close": 28.131214
    },
    {
      "date": "2026-04-24",
      "close": 27.497272
    },
    {
      "date": "2026-04-27",
      "close": 27.99254
    },
    {
      "date": "2026-04-28",
      "close": 28.061878
    },
    {
      "date": "2026-04-29",
      "close": 27.744905
    },
    {
      "date": "2026-04-30",
      "close": 28.279795
    },
    {
      "date": "2026-05-01",
      "close": 27.923203
    },
    {
      "date": "2026-05-04",
      "close": 27.398218
    },
    {
      "date": "2026-05-05",
      "close": 27.774624
    },
    {
      "date": "2026-05-06",
      "close": 27.943012
    },
    {
      "date": "2026-05-07",
      "close": 27.685474
    },
    {
      "date": "2026-05-08",
      "close": 27.368502
    },
    {
      "date": "2026-05-11",
      "close": 26.576075
    },
    {
      "date": "2026-05-12",
      "close": 26.893045
    },
    {
      "date": "2026-05-13",
      "close": 26.377966
    },
    {
      "date": "2026-05-14",
      "close": 26.546356
    },
    {
      "date": "2026-05-15",
      "close": 26.407682
    },
    {
      "date": "2026-05-18",
      "close": 26.714748
    },
    {
      "date": "2026-05-19",
      "close": 26.585979
    },
    {
      "date": "2026-05-20",
      "close": 27.269449
    },
    {
      "date": "2026-05-21",
      "close": 27.447744
    },
    {
      "date": "2026-05-22",
      "close": 27.56661
    },
    {
      "date": "2026-05-26",
      "close": 27.982635
    },
    {
      "date": "2026-05-27",
      "close": 27.824148
    },
    {
      "date": "2026-05-28",
      "close": 27.56661
    },
    {
      "date": "2026-05-29",
      "close": 27.735001
    },
    {
      "date": "2026-06-01",
      "close": 27.34
    },
    {
      "date": "2026-06-02",
      "close": 28.030001
    },
    {
      "date": "2026-06-03",
      "close": 27.4
    },
    {
      "date": "2026-06-04",
      "close": 28.43
    },
    {
      "date": "2026-06-05",
      "close": 28.540001
    },
    {
      "date": "2026-06-08",
      "close": 28.559999
    },
    {
      "date": "2026-06-09",
      "close": 28.6
    },
    {
      "date": "2026-06-10",
      "close": 28.58
    },
    {
      "date": "2026-06-11",
      "close": 28.889999
    },
    {
      "date": "2026-06-12",
      "close": 29.27
    },
    {
      "date": "2026-06-15",
      "close": 28.6
    },
    {
      "date": "2026-06-16",
      "close": 29
    },
    {
      "date": "2026-06-17",
      "close": 28.65
    },
    {
      "date": "2026-06-18",
      "close": 28.620001
    }
  ]
}
