{
  "ticker": "SPGI",
  "source": "https://query2.finance.yahoo.com/v8/finance/chart/SPGI?range=2y&interval=1d&events=history",
  "fetchedAt": "2026-06-19T01:16:35.624Z",
  "bars": [
    {
      "date": "2024-06-20",
      "close": 431.928772
    },
    {
      "date": "2024-06-21",
      "close": 432.430878
    },
    {
      "date": "2024-06-24",
      "close": 438.09201
    },
    {
      "date": "2024-06-25",
      "close": 441.84314
    },
    {
      "date": "2024-06-26",
      "close": 441.429565
    },
    {
      "date": "2024-06-27",
      "close": 441.9711
    },
    {
      "date": "2024-06-28",
      "close": 439.106079
    },
    {
      "date": "2024-07-01",
      "close": 439.421143
    },
    {
      "date": "2024-07-02",
      "close": 443.487335
    },
    {
      "date": "2024-07-03",
      "close": 442.49292
    },
    {
      "date": "2024-07-05",
      "close": 446.263733
    },
    {
      "date": "2024-07-08",
      "close": 448.843201
    },
    {
      "date": "2024-07-09",
      "close": 453.185059
    },
    {
      "date": "2024-07-10",
      "close": 458.796936
    },
    {
      "date": "2024-07-11",
      "close": 465.905396
    },
    {
      "date": "2024-07-12",
      "close": 470.926483
    },
    {
      "date": "2024-07-15",
      "close": 475.091125
    },
    {
      "date": "2024-07-16",
      "close": 481.234711
    },
    {
      "date": "2024-07-17",
      "close": 482.298004
    },
    {
      "date": "2024-07-18",
      "close": 477.198059
    },
    {
      "date": "2024-07-19",
      "close": 472.423065
    },
    {
      "date": "2024-07-22",
      "close": 479.787415
    },
    {
      "date": "2024-07-23",
      "close": 487.900055
    },
    {
      "date": "2024-07-24",
      "close": 474.214844
    },
    {
      "date": "2024-07-25",
      "close": 475.859039
    },
    {
      "date": "2024-07-26",
      "close": 482.248749
    },
    {
      "date": "2024-07-29",
      "close": 482.258636
    },
    {
      "date": "2024-07-30",
      "close": 480.959015
    },
    {
      "date": "2024-07-31",
      "close": 477.237427
    },
    {
      "date": "2024-08-01",
      "close": 482.947754
    },
    {
      "date": "2024-08-02",
      "close": 478.527191
    },
    {
      "date": "2024-08-05",
      "close": 464.694366
    },
    {
      "date": "2024-08-06",
      "close": 472.068604
    },
    {
      "date": "2024-08-07",
      "close": 470.729614
    },
    {
      "date": "2024-08-08",
      "close": 479.659424
    },
    {
      "date": "2024-08-09",
      "close": 480.959015
    },
    {
      "date": "2024-08-12",
      "close": 476.981476
    },
    {
      "date": "2024-08-13",
      "close": 482.120789
    },
    {
      "date": "2024-08-14",
      "close": 485.035004
    },
    {
      "date": "2024-08-15",
      "close": 485.310699
    },
    {
      "date": "2024-08-16",
      "close": 483.282562
    },
    {
      "date": "2024-08-19",
      "close": 488.07724
    },
    {
      "date": "2024-08-20",
      "close": 490.16449
    },
    {
      "date": "2024-08-21",
      "close": 491.267181
    },
    {
      "date": "2024-08-22",
      "close": 491.0112
    },
    {
      "date": "2024-08-23",
      "close": 492.852295
    },
    {
      "date": "2024-08-26",
      "close": 494.260193
    },
    {
      "date": "2024-08-27",
      "close": 498.481689
    },
    {
      "date": "2024-08-28",
      "close": 498.363312
    },
    {
      "date": "2024-08-29",
      "close": 501.105316
    },
    {
      "date": "2024-08-30",
      "close": 506.224335
    },
    {
      "date": "2024-09-03",
      "close": 503.817719
    },
    {
      "date": "2024-09-04",
      "close": 506.293396
    },
    {
      "date": "2024-09-05",
      "close": 509.932983
    },
    {
      "date": "2024-09-06",
      "close": 503.659912
    },
    {
      "date": "2024-09-09",
      "close": 508.779053
    },
    {
      "date": "2024-09-10",
      "close": 512.842651
    },
    {
      "date": "2024-09-11",
      "close": 508.759277
    },
    {
      "date": "2024-09-12",
      "close": 512.901855
    },
    {
      "date": "2024-09-13",
      "close": 512.349487
    },
    {
      "date": "2024-09-16",
      "close": 520.171082
    },
    {
      "date": "2024-09-17",
      "close": 515.239441
    },
    {
      "date": "2024-09-18",
      "close": 512.418518
    },
    {
      "date": "2024-09-19",
      "close": 517.054321
    },
    {
      "date": "2024-09-20",
      "close": 516.511841
    },
    {
      "date": "2024-09-23",
      "close": 513.957275
    },
    {
      "date": "2024-09-24",
      "close": 511.027863
    },
    {
      "date": "2024-09-25",
      "close": 507.782806
    },
    {
      "date": "2024-09-26",
      "close": 504.705475
    },
    {
      "date": "2024-09-27",
      "close": 505.711456
    },
    {
      "date": "2024-09-30",
      "close": 509.558197
    },
    {
      "date": "2024-10-01",
      "close": 505.218262
    },
    {
      "date": "2024-10-02",
      "close": 507.674286
    },
    {
      "date": "2024-10-03",
      "close": 507.565704
    },
    {
      "date": "2024-10-04",
      "close": 505.169006
    },
    {
      "date": "2024-10-07",
      "close": 499.49762
    },
    {
      "date": "2024-10-08",
      "close": 511.264496
    },
    {
      "date": "2024-10-09",
      "close": 514.341919
    },
    {
      "date": "2024-10-10",
      "close": 508.078705
    },
    {
      "date": "2024-10-11",
      "close": 514.874512
    },
    {
      "date": "2024-10-14",
      "close": 520.309143
    },
    {
      "date": "2024-10-15",
      "close": 521.226563
    },
    {
      "date": "2024-10-16",
      "close": 521.768982
    },
    {
      "date": "2024-10-17",
      "close": 511.866241
    },
    {
      "date": "2024-10-18",
      "close": 517.626404
    },
    {
      "date": "2024-10-21",
      "close": 516.038391
    },
    {
      "date": "2024-10-22",
      "close": 506.500549
    },
    {
      "date": "2024-10-23",
      "close": 503.936127
    },
    {
      "date": "2024-10-24",
      "close": 486.46814
    },
    {
      "date": "2024-10-25",
      "close": 483.903717
    },
    {
      "date": "2024-10-28",
      "close": 480.579773
    },
    {
      "date": "2024-10-29",
      "close": 480.096405
    },
    {
      "date": "2024-10-30",
      "close": 479.297546
    },
    {
      "date": "2024-10-31",
      "close": 473.793823
    },
    {
      "date": "2024-11-01",
      "close": 476.703522
    },
    {
      "date": "2024-11-04",
      "close": 479.129883
    },
    {
      "date": "2024-11-05",
      "close": 483.016052
    },
    {
      "date": "2024-11-06",
      "close": 483.292206
    },
    {
      "date": "2024-11-07",
      "close": 490.305023
    },
    {
      "date": "2024-11-08",
      "close": 495.946777
    },
    {
      "date": "2024-11-11",
      "close": 500.326172
    },
    {
      "date": "2024-11-12",
      "close": 496.587921
    },
    {
      "date": "2024-11-13",
      "close": 503.314728
    },
    {
      "date": "2024-11-14",
      "close": 503.659912
    },
    {
      "date": "2024-11-15",
      "close": 496.410431
    },
    {
      "date": "2024-11-18",
      "close": 496.124359
    },
    {
      "date": "2024-11-19",
      "close": 495.443756
    },
    {
      "date": "2024-11-20",
      "close": 496.252594
    },
    {
      "date": "2024-11-21",
      "close": 504.379913
    },
    {
      "date": "2024-11-22",
      "close": 507.427704
    },
    {
      "date": "2024-11-25",
      "close": 513.39502
    },
    {
      "date": "2024-11-26",
      "close": 515.726746
    },
    {
      "date": "2024-11-27",
      "close": 516.616089
    },
    {
      "date": "2024-11-29",
      "close": 516.270264
    },
    {
      "date": "2024-12-02",
      "close": 516.625916
    },
    {
      "date": "2024-12-03",
      "close": 512.001831
    },
    {
      "date": "2024-12-04",
      "close": 514.047119
    },
    {
      "date": "2024-12-05",
      "close": 507.753204
    },
    {
      "date": "2024-12-06",
      "close": 510.598785
    },
    {
      "date": "2024-12-09",
      "close": 507.219604
    },
    {
      "date": "2024-12-10",
      "close": 506.033997
    },
    {
      "date": "2024-12-11",
      "close": 510.104767
    },
    {
      "date": "2024-12-12",
      "close": 506.745392
    },
    {
      "date": "2024-12-13",
      "close": 499.710388
    },
    {
      "date": "2024-12-16",
      "close": 496.854889
    },
    {
      "date": "2024-12-17",
      "close": 494.53302
    },
    {
      "date": "2024-12-18",
      "close": 484.276947
    },
    {
      "date": "2024-12-19",
      "close": 480.749542
    },
    {
      "date": "2024-12-20",
      "close": 485.93689
    },
    {
      "date": "2024-12-23",
      "close": 492.299927
    },
    {
      "date": "2024-12-24",
      "close": 498.722382
    },
    {
      "date": "2024-12-26",
      "close": 498.752014
    },
    {
      "date": "2024-12-27",
      "close": 495.807587
    },
    {
      "date": "2024-12-30",
      "close": 492.072662
    },
    {
      "date": "2024-12-31",
      "close": 492.082611
    },
    {
      "date": "2025-01-02",
      "close": 489.582794
    },
    {
      "date": "2025-01-03",
      "close": 493.604218
    },
    {
      "date": "2025-01-06",
      "close": 488.288422
    },
    {
      "date": "2025-01-07",
      "close": 485.482361
    },
    {
      "date": "2025-01-08",
      "close": 489.938477
    },
    {
      "date": "2025-01-10",
      "close": 476.955414
    },
    {
      "date": "2025-01-13",
      "close": 476.826996
    },
    {
      "date": "2025-01-14",
      "close": 478.684509
    },
    {
      "date": "2025-01-15",
      "close": 490.590607
    },
    {
      "date": "2025-01-16",
      "close": 499.127411
    },
    {
      "date": "2025-01-17",
      "close": 495.866821
    },
    {
      "date": "2025-01-21",
      "close": 503.959015
    },
    {
      "date": "2025-01-22",
      "close": 504.858154
    },
    {
      "date": "2025-01-23",
      "close": 507.407349
    },
    {
      "date": "2025-01-24",
      "close": 507.614807
    },
    {
      "date": "2025-01-27",
      "close": 514.53125
    },
    {
      "date": "2025-01-28",
      "close": 514.234924
    },
    {
      "date": "2025-01-29",
      "close": 511.043365
    },
    {
      "date": "2025-01-30",
      "close": 517.287964
    },
    {
      "date": "2025-01-31",
      "close": 515.183411
    },
    {
      "date": "2025-02-03",
      "close": 512.189514
    },
    {
      "date": "2025-02-04",
      "close": 507.555573
    },
    {
      "date": "2025-02-05",
      "close": 508.128662
    },
    {
      "date": "2025-02-06",
      "close": 512.86145
    },
    {
      "date": "2025-02-07",
      "close": 512.950317
    },
    {
      "date": "2025-02-10",
      "close": 509.146393
    },
    {
      "date": "2025-02-11",
      "close": 534.055298
    },
    {
      "date": "2025-02-12",
      "close": 525.162842
    },
    {
      "date": "2025-02-13",
      "close": 535.843689
    },
    {
      "date": "2025-02-14",
      "close": 533.245117
    },
    {
      "date": "2025-02-18",
      "close": 537.276367
    },
    {
      "date": "2025-02-19",
      "close": 536.219177
    },
    {
      "date": "2025-02-20",
      "close": 529.03595
    },
    {
      "date": "2025-02-21",
      "close": 527.030151
    },
    {
      "date": "2025-02-24",
      "close": 526.852295
    },
    {
      "date": "2025-02-25",
      "close": 527.010498
    },
    {
      "date": "2025-02-26",
      "close": 523.862793
    },
    {
      "date": "2025-02-27",
      "close": 520.022095
    },
    {
      "date": "2025-02-28",
      "close": 528.317017
    },
    {
      "date": "2025-03-03",
      "close": 523.932007
    },
    {
      "date": "2025-03-04",
      "close": 511.559021
    },
    {
      "date": "2025-03-05",
      "close": 517.587219
    },
    {
      "date": "2025-03-06",
      "close": 508.985474
    },
    {
      "date": "2025-03-07",
      "close": 491.950317
    },
    {
      "date": "2025-03-10",
      "close": 483.427795
    },
    {
      "date": "2025-03-11",
      "close": 475.123016
    },
    {
      "date": "2025-03-12",
      "close": 473.400726
    },
    {
      "date": "2025-03-13",
      "close": 474.974579
    },
    {
      "date": "2025-03-14",
      "close": 481.547119
    },
    {
      "date": "2025-03-17",
      "close": 489.248047
    },
    {
      "date": "2025-03-18",
      "close": 485.407471
    },
    {
      "date": "2025-03-19",
      "close": 490.188385
    },
    {
      "date": "2025-03-20",
      "close": 492.148285
    },
    {
      "date": "2025-03-21",
      "close": 492.821381
    },
    {
      "date": "2025-03-24",
      "close": 498.819763
    },
    {
      "date": "2025-03-25",
      "close": 507.946106
    },
    {
      "date": "2025-03-26",
      "close": 502.640564
    },
    {
      "date": "2025-03-27",
      "close": 503.472046
    },
    {
      "date": "2025-03-28",
      "close": 497.404327
    },
    {
      "date": "2025-03-31",
      "close": 502.937531
    },
    {
      "date": "2025-04-01",
      "close": 505.590302
    },
    {
      "date": "2025-04-02",
      "close": 508.757782
    },
    {
      "date": "2025-04-03",
      "close": 484.407715
    },
    {
      "date": "2025-04-04",
      "close": 446.912598
    },
    {
      "date": "2025-04-07",
      "close": 433.856628
    },
    {
      "date": "2025-04-08",
      "close": 437.014191
    },
    {
      "date": "2025-04-09",
      "close": 469.174072
    },
    {
      "date": "2025-04-10",
      "close": 453.109039
    },
    {
      "date": "2025-04-11",
      "close": 460.414001
    },
    {
      "date": "2025-04-14",
      "close": 466.798492
    },
    {
      "date": "2025-04-15",
      "close": 465.927429
    },
    {
      "date": "2025-04-16",
      "close": 459.265808
    },
    {
      "date": "2025-04-17",
      "close": 458.176971
    },
    {
      "date": "2025-04-21",
      "close": 444.42807
    },
    {
      "date": "2025-04-22",
      "close": 461.681
    },
    {
      "date": "2025-04-23",
      "close": 465.452332
    },
    {
      "date": "2025-04-24",
      "close": 476.370239
    },
    {
      "date": "2025-04-25",
      "close": 475.123016
    },
    {
      "date": "2025-04-28",
      "close": 474.499451
    },
    {
      "date": "2025-04-29",
      "close": 486.76358
    },
    {
      "date": "2025-04-30",
      "close": 494.969299
    },
    {
      "date": "2025-05-01",
      "close": 493.860687
    },
    {
      "date": "2025-05-02",
      "close": 501.472534
    },
    {
      "date": "2025-05-05",
      "close": 500.759888
    },
    {
      "date": "2025-05-06",
      "close": 496.711426
    },
    {
      "date": "2025-05-07",
      "close": 500.571808
    },
    {
      "date": "2025-05-08",
      "close": 502.452484
    },
    {
      "date": "2025-05-09",
      "close": 502.571289
    },
    {
      "date": "2025-05-12",
      "close": 513.093262
    },
    {
      "date": "2025-05-13",
      "close": 510.331604
    },
    {
      "date": "2025-05-14",
      "close": 506.738525
    },
    {
      "date": "2025-05-15",
      "close": 514.003906
    },
    {
      "date": "2025-05-16",
      "close": 517.151672
    },
    {
      "date": "2025-05-19",
      "close": 518.953186
    },
    {
      "date": "2025-05-20",
      "close": 517.626709
    },
    {
      "date": "2025-05-21",
      "close": 505.085449
    },
    {
      "date": "2025-05-22",
      "close": 506.124847
    },
    {
      "date": "2025-05-23",
      "close": 504.837982
    },
    {
      "date": "2025-05-27",
      "close": 511.450165
    },
    {
      "date": "2025-05-28",
      "close": 507.225616
    },
    {
      "date": "2025-05-29",
      "close": 509.823761
    },
    {
      "date": "2025-05-30",
      "close": 508.594086
    },
    {
      "date": "2025-06-02",
      "close": 509.318054
    },
    {
      "date": "2025-06-03",
      "close": 508.038727
    },
    {
      "date": "2025-06-04",
      "close": 509.6651
    },
    {
      "date": "2025-06-05",
      "close": 511.46994
    },
    {
      "date": "2025-06-06",
      "close": 515.040039
    },
    {
      "date": "2025-06-09",
      "close": 510.716248
    },
    {
      "date": "2025-06-10",
      "close": 509.645264
    },
    {
      "date": "2025-06-11",
      "close": 509.704773
    },
    {
      "date": "2025-06-12",
      "close": 501.662262
    },
    {
      "date": "2025-06-13",
      "close": 497.318695
    },
    {
      "date": "2025-06-16",
      "close": 500.799469
    },
    {
      "date": "2025-06-17",
      "close": 496.902191
    },
    {
      "date": "2025-06-18",
      "close": 498.449188
    },
    {
      "date": "2025-06-20",
      "close": 500.006165
    },
    {
      "date": "2025-06-23",
      "close": 510.299805
    },
    {
      "date": "2025-06-24",
      "close": 518.619934
    },
    {
      "date": "2025-06-25",
      "close": 516.953979
    },
    {
      "date": "2025-06-26",
      "close": 510.736145
    },
    {
      "date": "2025-06-27",
      "close": 513.403748
    },
    {
      "date": "2025-06-30",
      "close": 522.904053
    },
    {
      "date": "2025-07-01",
      "close": 524.917236
    },
    {
      "date": "2025-07-02",
      "close": 521.267822
    },
    {
      "date": "2025-07-03",
      "close": 525.204773
    },
    {
      "date": "2025-07-07",
      "close": 525.77002
    },
    {
      "date": "2025-07-08",
      "close": 522.011597
    },
    {
      "date": "2025-07-09",
      "close": 524.332031
    },
    {
      "date": "2025-07-10",
      "close": 525.422974
    },
    {
      "date": "2025-07-11",
      "close": 522.685852
    },
    {
      "date": "2025-07-14",
      "close": 525.71051
    },
    {
      "date": "2025-07-15",
      "close": 517.93573
    },
    {
      "date": "2025-07-16",
      "close": 519.998413
    },
    {
      "date": "2025-07-17",
      "close": 520.990112
    },
    {
      "date": "2025-07-18",
      "close": 520.018372
    },
    {
      "date": "2025-07-21",
      "close": 517.777039
    },
    {
      "date": "2025-07-22",
      "close": 513.50293
    },
    {
      "date": "2025-07-23",
      "close": 521.287598
    },
    {
      "date": "2025-07-24",
      "close": 526.434448
    },
    {
      "date": "2025-07-25",
      "close": 530.500366
    },
    {
      "date": "2025-07-28",
      "close": 525.998047
    },
    {
      "date": "2025-07-29",
      "close": 526.374939
    },
    {
      "date": "2025-07-30",
      "close": 524.927124
    },
    {
      "date": "2025-07-31",
      "close": 546.515991
    },
    {
      "date": "2025-08-01",
      "close": 541.121277
    },
    {
      "date": "2025-08-04",
      "close": 558.336853
    },
    {
      "date": "2025-08-05",
      "close": 558.336853
    },
    {
      "date": "2025-08-06",
      "close": 557.880676
    },
    {
      "date": "2025-08-07",
      "close": 554.479187
    },
    {
      "date": "2025-08-08",
      "close": 552.237976
    },
    {
      "date": "2025-08-11",
      "close": 551.256226
    },
    {
      "date": "2025-08-12",
      "close": 554.40979
    },
    {
      "date": "2025-08-13",
      "close": 557.900513
    },
    {
      "date": "2025-08-14",
      "close": 559.45752
    },
    {
      "date": "2025-08-15",
      "close": 551.841309
    },
    {
      "date": "2025-08-18",
      "close": 546.625122
    },
    {
      "date": "2025-08-19",
      "close": 549.818298
    },
    {
      "date": "2025-08-20",
      "close": 552.396729
    },
    {
      "date": "2025-08-21",
      "close": 547.84491
    },
    {
      "date": "2025-08-22",
      "close": 552.029724
    },
    {
      "date": "2025-08-25",
      "close": 547.101135
    },
    {
      "date": "2025-08-26",
      "close": 548.680603
    },
    {
      "date": "2025-08-27",
      "close": 546.246765
    },
    {
      "date": "2025-08-28",
      "close": 543.942017
    },
    {
      "date": "2025-08-29",
      "close": 544.826172
    },
    {
      "date": "2025-09-02",
      "close": 536.084229
    },
    {
      "date": "2025-09-03",
      "close": 535.686829
    },
    {
      "date": "2025-09-04",
      "close": 536.700073
    },
    {
      "date": "2025-09-05",
      "close": 534.514587
    },
    {
      "date": "2025-09-08",
      "close": 542.273132
    },
    {
      "date": "2025-09-09",
      "close": 544.101013
    },
    {
      "date": "2025-09-10",
      "close": 536.33252
    },
    {
      "date": "2025-09-11",
      "close": 547.250183
    },
    {
      "date": "2025-09-12",
      "close": 540.643921
    },
    {
      "date": "2025-09-15",
      "close": 540.405579
    },
    {
      "date": "2025-09-16",
      "close": 537.723267
    },
    {
      "date": "2025-09-17",
      "close": 540.514771
    },
    {
      "date": "2025-09-18",
      "close": 504.453979
    },
    {
      "date": "2025-09-19",
      "close": 503.818207
    },
    {
      "date": "2025-09-22",
      "close": 502.238708
    },
    {
      "date": "2025-09-23",
      "close": 493.486725
    },
    {
      "date": "2025-09-24",
      "close": 487.506409
    },
    {
      "date": "2025-09-25",
      "close": 481.744598
    },
    {
      "date": "2025-09-26",
      "close": 483.969849
    },
    {
      "date": "2025-09-29",
      "close": 488.102448
    },
    {
      "date": "2025-09-30",
      "close": 483.50296
    },
    {
      "date": "2025-10-01",
      "close": 478.496185
    },
    {
      "date": "2025-10-02",
      "close": 473.48938
    },
    {
      "date": "2025-10-03",
      "close": 476.648407
    },
    {
      "date": "2025-10-06",
      "close": 475.198029
    },
    {
      "date": "2025-10-07",
      "close": 478.049133
    },
    {
      "date": "2025-10-08",
      "close": 479.251129
    },
    {
      "date": "2025-10-09",
      "close": 484.397003
    },
    {
      "date": "2025-10-10",
      "close": 482.896973
    },
    {
      "date": "2025-10-13",
      "close": 476.181488
    },
    {
      "date": "2025-10-14",
      "close": 483.483063
    },
    {
      "date": "2025-10-15",
      "close": 479.698181
    },
    {
      "date": "2025-10-16",
      "close": 468.939545
    },
    {
      "date": "2025-10-17",
      "close": 470.072021
    },
    {
      "date": "2025-10-20",
      "close": 474.443054
    },
    {
      "date": "2025-10-21",
      "close": 480.602203
    },
    {
      "date": "2025-10-22",
      "close": 476.578888
    },
    {
      "date": "2025-10-23",
      "close": 479.519409
    },
    {
      "date": "2025-10-24",
      "close": 486.224915
    },
    {
      "date": "2025-10-27",
      "close": 493.367554
    },
    {
      "date": "2025-10-28",
      "close": 490.427032
    },
    {
      "date": "2025-10-29",
      "close": 469.932953
    },
    {
      "date": "2025-10-30",
      "close": 488.330963
    },
    {
      "date": "2025-10-31",
      "close": 483.999664
    },
    {
      "date": "2025-11-03",
      "close": 493.744995
    },
    {
      "date": "2025-11-04",
      "close": 495.920593
    },
    {
      "date": "2025-11-05",
      "close": 493.824493
    },
    {
      "date": "2025-11-06",
      "close": 486.771301
    },
    {
      "date": "2025-11-07",
      "close": 493.148987
    },
    {
      "date": "2025-11-10",
      "close": 490.585968
    },
    {
      "date": "2025-11-11",
      "close": 494.450348
    },
    {
      "date": "2025-11-12",
      "close": 492.572784
    },
    {
      "date": "2025-11-13",
      "close": 499.645874
    },
    {
      "date": "2025-11-14",
      "close": 490.645538
    },
    {
      "date": "2025-11-17",
      "close": 485.72821
    },
    {
      "date": "2025-11-18",
      "close": 487.049438
    },
    {
      "date": "2025-11-19",
      "close": 487.565979
    },
    {
      "date": "2025-11-20",
      "close": 487.675293
    },
    {
      "date": "2025-11-21",
      "close": 490.347565
    },
    {
      "date": "2025-11-24",
      "close": 486.016266
    },
    {
      "date": "2025-11-25",
      "close": 491.898895
    },
    {
      "date": "2025-11-26",
      "close": 493.312317
    },
    {
      "date": "2025-11-28",
      "close": 496.517365
    },
    {
      "date": "2025-12-01",
      "close": 492.973877
    },
    {
      "date": "2025-12-02",
      "close": 488.932709
    },
    {
      "date": "2025-12-03",
      "close": 497.562531
    },
    {
      "date": "2025-12-04",
      "close": 494.685913
    },
    {
      "date": "2025-12-05",
      "close": 496.208801
    },
    {
      "date": "2025-12-08",
      "close": 489.818573
    },
    {
      "date": "2025-12-09",
      "close": 488.454926
    },
    {
      "date": "2025-12-10",
      "close": 489.042206
    },
    {
      "date": "2025-12-11",
      "close": 495.253265
    },
    {
      "date": "2025-12-12",
      "close": 498.707184
    },
    {
      "date": "2025-12-15",
      "close": 497.31369
    },
    {
      "date": "2025-12-16",
      "close": 497.542603
    },
    {
      "date": "2025-12-17",
      "close": 508.222839
    },
    {
      "date": "2025-12-18",
      "close": 504.36084
    },
    {
      "date": "2025-12-19",
      "close": 510.223511
    },
    {
      "date": "2025-12-22",
      "close": 519.480469
    },
    {
      "date": "2025-12-23",
      "close": 522.705444
    },
    {
      "date": "2025-12-24",
      "close": 523.302612
    },
    {
      "date": "2025-12-26",
      "close": 526.995422
    },
    {
      "date": "2025-12-29",
      "close": 527.642395
    },
    {
      "date": "2025-12-30",
      "close": 525.243591
    },
    {
      "date": "2025-12-31",
      "close": 520.167297
    },
    {
      "date": "2026-01-02",
      "close": 510.283234
    },
    {
      "date": "2026-01-05",
      "close": 530.429443
    },
    {
      "date": "2026-01-06",
      "close": 537.148132
    },
    {
      "date": "2026-01-07",
      "close": 535.008118
    },
    {
      "date": "2026-01-08",
      "close": 539.049316
    },
    {
      "date": "2026-01-09",
      "close": 539.42749
    },
    {
      "date": "2026-01-12",
      "close": 541.95575
    },
    {
      "date": "2026-01-13",
      "close": 539.646484
    },
    {
      "date": "2026-01-14",
      "close": 542.473328
    },
    {
      "date": "2026-01-15",
      "close": 542.901367
    },
    {
      "date": "2026-01-16",
      "close": 543.817078
    },
    {
      "date": "2026-01-20",
      "close": 516.633667
    },
    {
      "date": "2026-01-21",
      "close": 528.697449
    },
    {
      "date": "2026-01-22",
      "close": 537.297424
    },
    {
      "date": "2026-01-23",
      "close": 531.136108
    },
    {
      "date": "2026-01-26",
      "close": 532.748596
    },
    {
      "date": "2026-01-27",
      "close": 524.228333
    },
    {
      "date": "2026-01-28",
      "close": 525.671631
    },
    {
      "date": "2026-01-29",
      "close": 526.179199
    },
    {
      "date": "2026-01-30",
      "close": 525.343079
    },
    {
      "date": "2026-02-02",
      "close": 525.213684
    },
    {
      "date": "2026-02-03",
      "close": 466.039337
    },
    {
      "date": "2026-02-04",
      "close": 463.351868
    },
    {
      "date": "2026-02-05",
      "close": 449.615845
    },
    {
      "date": "2026-02-06",
      "close": 437.243439
    },
    {
      "date": "2026-02-09",
      "close": 442.130707
    },
    {
      "date": "2026-02-10",
      "close": 399.220551
    },
    {
      "date": "2026-02-11",
      "close": 388.948395
    },
    {
      "date": "2026-02-12",
      "close": 395.358551
    },
    {
      "date": "2026-02-13",
      "close": 407.641327
    },
    {
      "date": "2026-02-17",
      "close": 408.547119
    },
    {
      "date": "2026-02-18",
      "close": 417.435699
    },
    {
      "date": "2026-02-19",
      "close": 414.738281
    },
    {
      "date": "2026-02-20",
      "close": 415.544556
    },
    {
      "date": "2026-02-23",
      "close": 402.903412
    },
    {
      "date": "2026-02-24",
      "close": 416.330872
    },
    {
      "date": "2026-02-25",
      "close": 422.62619
    },
    {
      "date": "2026-02-26",
      "close": 436.473969
    },
    {
      "date": "2026-02-27",
      "close": 440.85379
    },
    {
      "date": "2026-03-02",
      "close": 442.050995
    },
    {
      "date": "2026-03-03",
      "close": 442.958893
    },
    {
      "date": "2026-03-04",
      "close": 444.465393
    },
    {
      "date": "2026-03-05",
      "close": 450.062347
    },
    {
      "date": "2026-03-06",
      "close": 451.309448
    },
    {
      "date": "2026-03-09",
      "close": 444.24588
    },
    {
      "date": "2026-03-10",
      "close": 434.428741
    },
    {
      "date": "2026-03-11",
      "close": 427.963776
    },
    {
      "date": "2026-03-12",
      "close": 418.725311
    },
    {
      "date": "2026-03-13",
      "close": 421.50882
    },
    {
      "date": "2026-03-16",
      "close": 425.599304
    },
    {
      "date": "2026-03-17",
      "close": 431.93454
    },
    {
      "date": "2026-03-18",
      "close": 425.6492
    },
    {
      "date": "2026-03-19",
      "close": 425.15036
    },
    {
      "date": "2026-03-20",
      "close": 423.444305
    },
    {
      "date": "2026-03-23",
      "close": 427.873993
    },
    {
      "date": "2026-03-24",
      "close": 410.245056
    },
    {
      "date": "2026-03-25",
      "close": 407.531372
    },
    {
      "date": "2026-03-26",
      "close": 411.492157
    },
    {
      "date": "2026-03-27",
      "close": 405.296539
    },
    {
      "date": "2026-03-30",
      "close": 416.620209
    },
    {
      "date": "2026-03-31",
      "close": 424.352203
    },
    {
      "date": "2026-04-01",
      "close": 424.182617
    },
    {
      "date": "2026-04-02",
      "close": 430.158691
    },
    {
      "date": "2026-04-06",
      "close": 433.101807
    },
    {
      "date": "2026-04-07",
      "close": 429.061249
    },
    {
      "date": "2026-04-08",
      "close": 435.945221
    },
    {
      "date": "2026-04-09",
      "close": 423.334564
    },
    {
      "date": "2026-04-10",
      "close": 414.455261
    },
    {
      "date": "2026-04-13",
      "close": 429.081177
    },
    {
      "date": "2026-04-14",
      "close": 424.252411
    },
    {
      "date": "2026-04-15",
      "close": 429.580017
    },
    {
      "date": "2026-04-16",
      "close": 435.775604
    },
    {
      "date": "2026-04-17",
      "close": 441.542206
    },
    {
      "date": "2026-04-20",
      "close": 441.711792
    },
    {
      "date": "2026-04-21",
      "close": 443.637329
    },
    {
      "date": "2026-04-22",
      "close": 448.01712
    },
    {
      "date": "2026-04-23",
      "close": 438.010406
    },
    {
      "date": "2026-04-24",
      "close": 435.775604
    },
    {
      "date": "2026-04-27",
      "close": 436.20462
    },
    {
      "date": "2026-04-28",
      "close": 432.463318
    },
    {
      "date": "2026-04-29",
      "close": 432.18396
    },
    {
      "date": "2026-04-30",
      "close": 430.228546
    },
    {
      "date": "2026-05-01",
      "close": 425.070526
    },
    {
      "date": "2026-05-04",
      "close": 423.76358
    },
    {
      "date": "2026-05-05",
      "close": 422.88562
    },
    {
      "date": "2026-05-06",
      "close": 422.586304
    },
    {
      "date": "2026-05-07",
      "close": 427.684448
    },
    {
      "date": "2026-05-08",
      "close": 419.144318
    },
    {
      "date": "2026-05-11",
      "close": 420.022278
    },
    {
      "date": "2026-05-12",
      "close": 423.184937
    },
    {
      "date": "2026-05-13",
      "close": 405.605835
    },
    {
      "date": "2026-05-14",
      "close": 402.981964
    },
    {
      "date": "2026-05-15",
      "close": 402.213715
    },
    {
      "date": "2026-05-18",
      "close": 416.440613
    },
    {
      "date": "2026-05-19",
      "close": 409.446899
    },
    {
      "date": "2026-05-20",
      "close": 416.041565
    },
    {
      "date": "2026-05-21",
      "close": 414.764526
    },
    {
      "date": "2026-05-22",
      "close": 416.630188
    },
    {
      "date": "2026-05-26",
      "close": 411.522064
    },
    {
      "date": "2026-05-27",
      "close": 414.834351
    },
    {
      "date": "2026-05-28",
      "close": 416.709991
    },
    {
      "date": "2026-05-29",
      "close": 424
    },
    {
      "date": "2026-06-01",
      "close": 428.559998
    },
    {
      "date": "2026-06-02",
      "close": 417.459991
    },
    {
      "date": "2026-06-03",
      "close": 412.290009
    },
    {
      "date": "2026-06-04",
      "close": 420.119995
    },
    {
      "date": "2026-06-05",
      "close": 424.440002
    },
    {
      "date": "2026-06-08",
      "close": 417.089996
    },
    {
      "date": "2026-06-09",
      "close": 424.820007
    },
    {
      "date": "2026-06-10",
      "close": 426.380005
    },
    {
      "date": "2026-06-11",
      "close": 413.339996
    },
    {
      "date": "2026-06-12",
      "close": 418.910004
    },
    {
      "date": "2026-06-15",
      "close": 424.070007
    },
    {
      "date": "2026-06-16",
      "close": 433.25
    },
    {
      "date": "2026-06-17",
      "close": 418.019989
    },
    {
      "date": "2026-06-18",
      "close": 410.920013
    }
  ]
}
